{"code":1,"data":{"5211062724776":[{"district_id":"23008856","longitude":"121.40063248908","latitude":"37.541261397777","resblock_id":"5211062724776","project_name":"wdgckaasta","resblock_name":"\u4e07\u8fbe\u5e7f\u573a","min_frame_area":"140","max_frame_area":"233","special_tags":[],"average_price":"18000","cover_pic":"http:\/\/image1.ljcdn.com\/xf-resblock\/0f9f86eb-975e-40e9-977b-5201d133d240.jpg.200x200.jpg","rooms":"6\u5c45\/5\u5c45\/4\u5c45","resblock_frame_area":"\u5efa\u9762 140~233m\u00b2","house_type":"\u666e\u901a\u4f4f\u5b85","url":"\/loupan\/p_wdgckaasta\/","price_show_config":"1","show_price":"18000","show_price_unit":"\u5143\/\u5e73","show_price_desc":"\u5747\u4ef7"}],"5211062859665":[{"district_id":"23008859","longitude":"121.4320880383","latitude":"37.529024338556","resblock_id":"5211062859665","project_name":"ydlskaaskr","resblock_name":"\u4e91\u9876\u84dd\u5c71","min_frame_area":"271","max_frame_area":"271","special_tags":["\u5168\u6b3e9.8\u6298  \u8d37\u6b3e9.9\u6298"],"average_price":"16000","cover_pic":"http:\/\/image1.ljcdn.com\/xf-resblock\/974b0e5a-eb93-4bee-90ea-a516c84e7dc4.jpg.200x200.jpg","rooms":"3\u5c45","resblock_frame_area":"\u5efa\u9762 271m\u00b2","house_type":"\u666e\u901a\u4f4f\u5b85","url":"\/loupan\/p_ydlskaaskr\/","price_show_config":"1","show_price":"16000","show_price_unit":"\u5143\/\u5e73","show_price_desc":"\u5747\u4ef7"}],"5212025478262353":[{"district_id":"23008859","longitude":"121.44598","latitude":"37.519311","resblock_id":"5212025478262353","project_name":"xllccyaastf","resblock_name":"\u7965\u9686\u7eff\u57ce\u8bda\u56ed","min_frame_area":"140","max_frame_area":"210","special_tags":["\u5168\u6b3e9.8\u6298  \u8d37\u6b3e9.9\u6298"],"average_price":"15500","cover_pic":"http:\/\/image1.ljcdn.com\/xf-resblock\/7c4dccaa-55fc-4b8c-af60-9d61aa01d8a5.jpg.200x200.jpg","rooms":"4\u5c45\/3\u5c45","resblock_frame_area":"\u5efa\u9762 140~210m\u00b2","house_type":"\u666e\u901a\u4f4f\u5b85","url":"\/loupan\/p_xllccyaastf\/","price_show_config":"1","show_price":"15500","show_price_unit":"\u5143\/\u5e73","show_price_desc":"\u5747\u4ef7"}],"5212855418827265":[{"district_id":"23008856","longitude":"121.369468","latitude":"37.550681","resblock_id":"5212855418827265","project_name":"wkfcgyaawaa","resblock_name":"\u4e07\u79d1\u7fe1\u7fe0\u516c\u56ed","min_frame_area":"120","max_frame_area":"120","special_tags":[],"average_price":"15500","cover_pic":"http:\/\/image1.ljcdn.com\/xf-resblock\/78a394e8-a947-48c8-8f32-33891b5d69ba.jpg.200x200.jpg","rooms":"3\u5c45","resblock_frame_area":"\u5efa\u9762 120m\u00b2","house_type":"\u666e\u901a\u4f4f\u5b85","url":"\/loupan\/p_wkfcgyaawaa\/","price_show_config":"1","show_price":"15500","show_price_unit":"\u5143\/\u5e73","show_price_desc":"\u5747\u4ef7"}],"5214554345255860":[{"district_id":"23008856","longitude":"121.380881","latitude":"37.5193","resblock_id":"5214554345255860","project_name":"mzszaazcr","resblock_name":"\u660e\u73e0\u5c71\u5e84","min_frame_area":"138","max_frame_area":"256","special_tags":[],"average_price":"14000","cover_pic":"http:\/\/image1.ljcdn.com\/xf-resblock\/d19da313-9383-4fae-b844-17dad15064e0.jpg.200x200.jpg","rooms":"5\u5c45\/4\u5c45\/3\u5c45","resblock_frame_area":"\u5efa\u9762 138~256m\u00b2","house_type":"\u666e\u901a\u4f4f\u5b85","url":"\/loupan\/p_mzszaazcr\/","price_show_config":"1","show_price":"14000","show_price_unit":"\u5143\/\u5e73","show_price_desc":"\u5747\u4ef7"}],"5212025478261881":[{"district_id":"23008859","longitude":"121.44039","latitude":"37.528907","resblock_id":"5212025478261881","project_name":"ghlaaskg","resblock_name":"\u89c2\u6d77\u8def8\u53f7","min_frame_area":"140","max_frame_area":"149","special_tags":["\u5168\u6b3e9.7\u6298  \u8d37\u6b3e9.8\u6298"],"average_price":"12500","cover_pic":"http:\/\/image1.ljcdn.com\/xf-resblock\/40561d78-51d2-44ec-9731-1168dce1c39f.jpg.200x200.jpg","rooms":"3\u5c45","resblock_frame_area":"\u5efa\u9762 140~149m\u00b2","house_type":"\u666e\u901a\u4f4f\u5b85","url":"\/loupan\/p_ghlaaskg\/","price_show_config":"1","show_price":"12500","show_price_unit":"\u5143\/\u5e73","show_price_desc":"\u5747\u4ef7"}],"5211063046677":[{"district_id":"23008859","longitude":"121.46818183752","latitude":"37.436364984134","resblock_id":"5211063046677","project_name":"jdglsjyxaasjh","resblock_name":"\u91d1\u5730\u683c\u6797\u4e16\u754c","min_frame_area":"77","max_frame_area":"145","special_tags":[],"average_price":"12000","cover_pic":"http:\/\/image1.ljcdn.com\/xf-resblock\/cd6f2897-4cd2-480f-96ad-4b5593c55ac7.jpg.200x200.jpg","rooms":"4\u5c45\/3\u5c45\/2\u5c45","resblock_frame_area":"\u5efa\u9762 77~145m\u00b2","house_type":"\u666e\u901a\u4f4f\u5b85","url":"\/loupan\/p_jdglsjyxaasjh\/","price_show_config":"1","show_price":"12000","show_price_unit":"\u5143\/\u5e73","show_price_desc":"\u5747\u4ef7"}],"5211062622771":[{"district_id":"23008856","longitude":"121.35673731267","latitude":"37.477837403406","resblock_id":"5211062622771","project_name":"aasnn","resblock_name":"\u4fdd\u5229\u7d2b\u8587\u90e1","min_frame_area":"101","max_frame_area":"150","special_tags":["9.9\u6298"],"average_price":"12000","cover_pic":"http:\/\/image1.ljcdn.com\/xf-resblock\/8f29d830-6cb5-4110-833a-7f5547493d6a.jpg.200x200.jpg","rooms":"4\u5c45\/3\u5c45","resblock_frame_area":"\u5efa\u9762 101~150m\u00b2","house_type":"\u666e\u901a\u4f4f\u5b85","url":"\/loupan\/p_aasnn\/","price_show_config":"1","show_price":"12000","show_price_unit":"\u5143\/\u5e73","show_price_desc":"\u5747\u4ef7"}],"5212040952361825":[{"district_id":"23008856","longitude":"121.380052","latitude":"37.524492","resblock_id":"5212040952361825","project_name":"bsyhzlyaasno","resblock_name":"\u4f34\u5c71\u58f9\u53f7\u7d2b\u6797\u56ed","min_frame_area":"154","max_frame_area":"154","special_tags":["\u5168\u6b3e9.7\u6298  \u8d37\u6b3e9.8\u6298"],"average_price":"12000","cover_pic":"http:\/\/image1.ljcdn.com\/xf-resblock\/27f4260f-9de5-47b8-bbe4-836812aa18a1.jpg.200x200.jpg","rooms":"3\u5c45","resblock_frame_area":"\u5efa\u9762 154m\u00b2","house_type":"\u666e\u901a\u4f4f\u5b85","url":"\/loupan\/p_bsyhzlyaasno\/","price_show_config":"1","show_price":"12000","show_price_unit":"\u5143\/\u5e73","show_price_desc":"\u5747\u4ef7"}],"5211062495940":[{"district_id":"23009087","longitude":"121.24689029354","latitude":"37.575121702646","resblock_id":"5211062495940","project_name":"aasrh","resblock_name":"\u6052\u8fbe\u6d77\u946b\u82b1\u56ed","min_frame_area":"148","max_frame_area":"218","special_tags":[],"average_price":"11000","cover_pic":"http:\/\/image1.ljcdn.com\/xf-resblock\/c0a6e9aa-8583-45dd-8340-0df2866e73f8.jpg.200x200.jpg","rooms":"3\u5c45","resblock_frame_area":"\u5efa\u9762 148~218m\u00b2","house_type":"\u666e\u901a\u4f4f\u5b85","url":"\/loupan\/p_aasrh\/","price_show_config":"1","show_price":"11000","show_price_unit":"\u5143\/\u5e73","show_price_desc":"\u5747\u4ef7"}],"5211062696860":[{"district_id":"23008856","longitude":"121.38993362374","latitude":"37.544427613627","resblock_id":"5211062696860","project_name":"aastb","resblock_name":"\u540d\u4ed5\u8c6a\u5ead","min_frame_area":"34","max_frame_area":"78","special_tags":[],"average_price":"10000","cover_pic":"http:\/\/image1.ljcdn.com\/xf-resblock\/3e47b058-9347-4b18-b60c-3048d1e5b3cc.jpg.200x200.jpg","rooms":"2\u5c45\/1\u5c45","resblock_frame_area":"\u5efa\u9762 34~78m\u00b2","house_type":"\u666e\u901a\u4f4f\u5b85","url":"\/loupan\/p_aastb\/","price_show_config":"1","show_price":"10000","show_price_unit":"\u5143\/\u5e73","show_price_desc":"\u5747\u4ef7"}],"5211062519481":[{"district_id":"23008856","longitude":"121.36823227077","latitude":"37.520623230107","resblock_id":"5211062519481","project_name":"ygsckaasni","resblock_name":"\u9633\u5149\u4e0a\u57ce","min_frame_area":"57","max_frame_area":"141","special_tags":["\u5168\u6b3e9.8\u6298  \u8d37\u6b3e9.9\u6298"],"average_price":"9400","cover_pic":"http:\/\/image1.ljcdn.com\/xf-resblock\/2714613a-abd2-4a9b-a406-a3f614ea9f10.jpg.200x200.jpg","rooms":"3\u5c45\/2\u5c45\/1\u5c45","resblock_frame_area":"\u5efa\u9762 57~141m\u00b2","house_type":"\u666e\u901a\u4f4f\u5b85","url":"\/loupan\/p_ygsckaasni\/","price_show_config":"1","show_price":"9400","show_price_unit":"\u5143\/\u5e73","show_price_desc":"\u5747\u4ef7"}],"5211062645893":[{"district_id":"23008856","longitude":"121.3731959734","latitude":"37.554698733934","resblock_id":"5211062645893","project_name":"jcyykaazbr","resblock_name":"\u5efa\u57ce\u9890\u82d1","min_frame_area":"84","max_frame_area":"134","special_tags":["\u8d2d\u623f\u8865\u8d34"],"average_price":"8800","cover_pic":"http:\/\/image1.ljcdn.com\/xf-resblock\/7b99e3db-d26e-46e4-918a-6697a6204362.jpg.200x200.jpg","rooms":"3\u5c45\/2\u5c45","resblock_frame_area":"\u5efa\u9762 84~134m\u00b2","house_type":"\u666e\u901a\u4f4f\u5b85","url":"\/loupan\/p_jcyykaazbr\/","price_show_config":"1","show_price":"8800","show_price_unit":"\u5143\/\u5e73","show_price_desc":"\u5747\u4ef7"}],"5211063021120":[{"district_id":"23008859","longitude":"121.43313200025","latitude":"37.449574928084","resblock_id":"5211063021120","project_name":"aasrw","resblock_name":"\u6696\u5c71\u56fd\u9645","min_frame_area":"85","max_frame_area":"127","special_tags":["\u5168\u6b3e9.7\u6298  \u8d37\u6b3e9.8\u6298"],"average_price":"8700","cover_pic":"http:\/\/image1.ljcdn.com\/xf-resblock\/53158563-05dc-4867-923c-5a67268c6179.jpg.200x200.jpg","rooms":"4\u5c45\/3\u5c45\/2\u5c45","resblock_frame_area":"\u5efa\u9762 85~127m\u00b2","house_type":"\u666e\u901a\u4f4f\u5b85","url":"\/loupan\/p_aasrw\/","price_show_config":"1","show_price":"8700","show_price_unit":"\u5143\/\u5e73","show_price_desc":"\u5747\u4ef7"}],"5211063029864":[{"district_id":"23008856","longitude":"121.36816343306","latitude":"37.487418404029","resblock_id":"5211063029864","project_name":"jxtjxjykaasmz","resblock_name":"\u91d1\u8c61\u6cf0\u5409\u7965\u5bb6\u56ed","min_frame_area":"139","max_frame_area":"139","special_tags":["9.5\u6298"],"average_price":"8600","cover_pic":"http:\/\/image1.ljcdn.com\/xf-resblock\/b732feff-586d-4143-973d-cdaefbb8acc8.jpg.200x200.jpg","rooms":"3\u5c45","resblock_frame_area":"\u5efa\u9762 139m\u00b2","house_type":"\u666e\u901a\u4f4f\u5b85","url":"\/loupan\/p_jxtjxjykaasmz\/","price_show_config":"1","show_price":"8600","show_price_unit":"\u5143\/\u5e73","show_price_desc":"\u5747\u4ef7"}],"5212039730507593":[{"district_id":"23009088","longitude":"121.534668","latitude":"37.447351","resblock_id":"5212039730507593","project_name":"jxtlyfaaslg","resblock_name":"\u91d1\u8c61\u6cf0\u00b7\u5341\u91cc\u6d0b\u623f","min_frame_area":"158","max_frame_area":"179","special_tags":["\u6bcf\u5e73\u7c73\u4f18\u60e0"],"average_price":"8500","cover_pic":"http:\/\/image1.ljcdn.com\/xf-resblock\/f378441c-2b0a-4354-9559-18f1d2688000.jpg.200x200.jpg","rooms":"4\u5c45","resblock_frame_area":"\u5efa\u9762 158~179m\u00b2","house_type":"\u666e\u901a\u4f4f\u5b85","url":"\/loupan\/p_jxtlyfaaslg\/","price_show_config":"1","show_price":"8500","show_price_unit":"\u5143\/\u5e73","show_price_desc":"\u5747\u4ef7"}],"5212065340665612":[{"district_id":"23009087","longitude":"121.21094","latitude":"37.582763","resblock_id":"5212065340665612","project_name":"zhhbjraasra","resblock_name":"\u632f\u534e\u6d77\u6ee8\u5047\u65e5\u82b1\u56ed","min_frame_area":"88","max_frame_area":"179","special_tags":[],"average_price":"8500","cover_pic":"http:\/\/image1.ljcdn.com\/xf-resblock\/3e4eaace-7510-45e5-8cd4-59e08474e9ea.jpg.200x200.jpg","rooms":"4\u5c45\/2\u5c45","resblock_frame_area":"\u5efa\u9762 88~179m\u00b2","house_type":"\u666e\u901a\u4f4f\u5b85","url":"\/loupan\/p_zhhbjraasra\/","price_show_config":"1","show_price":"8500","show_price_unit":"\u5143\/\u5e73","show_price_desc":"\u5747\u4ef7"}],"5211062491857":[{"district_id":"23009087","longitude":"121.26243026246","latitude":"37.576142562211","resblock_id":"5211062491857","project_name":"tthyaayqt","resblock_name":"\u542c\u6d9b\u82b1\u56ed","min_frame_area":"167","max_frame_area":"219","special_tags":["\u5168\u6b3e9.6\u6298  \u8d37\u6b3e9.7\u6298"],"average_price":"8500","cover_pic":"http:\/\/image1.ljcdn.com\/xf-resblock\/37b2108e-ecdb-489a-abfb-d518dbeaaf68.JPG.200x200.jpg","rooms":"4\u5c45\/3\u5c45","resblock_frame_area":"\u5efa\u9762 167~219m\u00b2","house_type":"\u666e\u901a\u4f4f\u5b85","url":"\/loupan\/p_tthyaayqt\/","price_show_config":"1","show_price":"8500","show_price_unit":"\u5143\/\u5e73","show_price_desc":"\u5747\u4ef7"}],"5212040444588205":[{"district_id":"23008856","longitude":"121.357164","latitude":"37.505042","resblock_id":"5212040444588205","project_name":"zzggaaste","resblock_name":"\u4e2d\u6b63\u516c\u9986","min_frame_area":"84","max_frame_area":"266","special_tags":[],"average_price":"8300","cover_pic":"http:\/\/image1.ljcdn.com\/xf-resblock\/6b1ee757-cda7-4652-b081-7f475c719bec.jpg.200x200.jpg","rooms":"4\u5c45\/3\u5c45\/2\u5c45","resblock_frame_area":"\u5efa\u9762 84~266m\u00b2","house_type":"\u666e\u901a\u4f4f\u5b85","url":"\/loupan\/p_zzggaaste\/","price_show_config":"1","show_price":"8300","show_price_unit":"\u5143\/\u5e73","show_price_desc":"\u5747\u4ef7"}],"5212025478261935":[{"district_id":"23008859","longitude":"121.415942","latitude":"37.493207","resblock_id":"5212025478261935","project_name":"tlzyaasjq","resblock_name":"\u5929\u7c41\u4e2d\u56ed","min_frame_area":"79","max_frame_area":"79","special_tags":[],"average_price":"8200","cover_pic":"http:\/\/image1.ljcdn.com\/xf-resblock\/f35db7d4-f142-45bf-9f84-c559ec3bebf5.jpg.200x200.jpg","rooms":"2\u5c45","resblock_frame_area":"\u5efa\u9762 79m\u00b2","house_type":"\u666e\u901a\u4f4f\u5b85","url":"\/loupan\/p_tlzyaasjq\/","price_show_config":"1","show_price":"8200","show_price_unit":"\u5143\/\u5e73","show_price_desc":"\u5747\u4ef7"}],"5212024341606748":[{"district_id":"23008856","longitude":"121.383198","latitude":"37.491947","resblock_id":"5212024341606748","project_name":"sslctyaasms","resblock_name":"\u5c71\u6c34\u9f99\u57ce\u5929\u60a6","min_frame_area":"80","max_frame_area":"126","special_tags":["\u5168\u6b3e9.4\u6298  \u8d37\u6b3e9.5\u6298"],"average_price":"8100","cover_pic":"http:\/\/image1.ljcdn.com\/xf-resblock\/bf1baf22-4367-419e-ab3c-1dad6d4dc012.jpg.200x200.jpg","rooms":"3\u5c45\/2\u5c45","resblock_frame_area":"\u5efa\u9762 80~126m\u00b2","house_type":"\u666e\u901a\u4f4f\u5b85","url":"\/loupan\/p_sslctyaasms\/","price_show_config":"1","show_price":"8100","show_price_unit":"\u5143\/\u5e73","show_price_desc":"\u5747\u4ef7"}],"5211951385095961":[{"district_id":"23008856","longitude":"121.377243","latitude":"37.555212","resblock_id":"5211951385095961","project_name":"dfjyaasmh","resblock_name":"\u5fb7\u86a8\u5bb6\u56ed","min_frame_area":"85","max_frame_area":"105","special_tags":[],"average_price":"8000","cover_pic":"http:\/\/image1.ljcdn.com\/xf-resblock\/9d33a607-e026-456b-ad01-633701e7232a.jpg.200x200.jpg","rooms":"3\u5c45\/2\u5c45","resblock_frame_area":"\u5efa\u9762 85~105m\u00b2","house_type":"\u666e\u901a\u4f4f\u5b85","url":"\/loupan\/p_dfjyaasmh\/","price_show_config":"1","show_price":"8000","show_price_unit":"\u5143\/\u5e73","show_price_desc":"\u5747\u4ef7"}],"527830398315591":[{"district_id":"23008856","longitude":"121.38186","latitude":"37.610629","resblock_id":"527830398315591","project_name":"wkqntqaasnm","resblock_name":"\u4e07\u79d1\u9752\u5e74\u7279\u533a","min_frame_area":"80","max_frame_area":"126","special_tags":[],"average_price":"8000","cover_pic":"http:\/\/image1.ljcdn.com\/xf-resblock\/44ef7304-9c87-416a-b01e-7be8d9b47395.jpg.200x200.jpg","rooms":"3\u5c45\/2\u5c45","resblock_frame_area":"\u5efa\u9762 80~126m\u00b2","house_type":"\u666e\u901a\u4f4f\u5b85","url":"\/loupan\/p_wkqntqaasnm\/","price_show_config":"1","show_price":"8000","show_price_unit":"\u5143\/\u5e73","show_price_desc":"\u5747\u4ef7"}],"5212040512483088":[{"district_id":"23008859","longitude":"121.482987","latitude":"37.454103","resblock_id":"5212040512483088","project_name":"jhmyaassb","resblock_name":"\u91d1\u6d77\u540d\u56ed","min_frame_area":"204","max_frame_area":"204","special_tags":[],"average_price":"8000","cover_pic":"http:\/\/image1.ljcdn.com\/xf-resblock\/15a975e8-322a-414d-a98c-6d5e16206a2e.jpg.200x200.jpg","rooms":"4\u5c45","resblock_frame_area":"\u5efa\u9762 204m\u00b2","house_type":"\u666e\u901a\u4f4f\u5b85","url":"\/loupan\/p_jhmyaassb\/","price_show_config":"1","show_price":"8000","show_price_unit":"\u5143\/\u5e73","show_price_desc":"\u5747\u4ef7"}],"5212042694569109":[{"district_id":"23008856","longitude":"121.340804","latitude":"37.549633","resblock_id":"5212042694569109","project_name":"dxrfyaasof","resblock_name":"\u5fb7\u4fe1\u6da6\u798f\u56ed","min_frame_area":"46","max_frame_area":"107","special_tags":["\u5168\u6b3e9.8\u6298  \u8d37\u6b3e9.9\u6298"],"average_price":"7900","cover_pic":"http:\/\/image1.ljcdn.com\/xf-resblock\/43c405be-05ad-4861-b23b-0136f2739c89.jpg.200x200.jpg","rooms":"3\u5c45\/2\u5c45\/1\u5c45","resblock_frame_area":"\u5efa\u9762 46~107m\u00b2","house_type":"\u666e\u901a\u4f4f\u5b85","url":"\/loupan\/p_dxrfyaasof\/","price_show_config":"1","show_price":"7900","show_price_unit":"\u5143\/\u5e73","show_price_desc":"\u5747\u4ef7"}],"5212040738713369":[{"district_id":"23009088","longitude":"121.558143","latitude":"37.428846","resblock_id":"5212040738713369","project_name":"bymdaaslr","resblock_name":"\u535a\u6e90\u540d\u90fd","min_frame_area":"89","max_frame_area":"126","special_tags":[],"average_price":"7800","cover_pic":"http:\/\/image1.ljcdn.com\/xf-resblock\/12464fba-b867-4ed7-8868-7317a886e9d9.jpg.200x200.jpg","rooms":"3\u5c45\/2\u5c45","resblock_frame_area":"\u5efa\u9762 89~126m\u00b2","house_type":"\u666e\u901a\u4f4f\u5b85","url":"\/loupan\/p_bymdaaslr\/","price_show_config":"1","show_price":"7800","show_price_unit":"\u5143\/\u5e73","show_price_desc":"\u5747\u4ef7"}],"5211062861153":[{"district_id":"23008856","longitude":"121.368772964","latitude":"37.510274661187","resblock_id":"5211062861153","project_name":"jdjykaasmn","resblock_name":"\u91d1\u5e1d\u4f73\u56ed","min_frame_area":"84","max_frame_area":"119","special_tags":["\u6bcf\u5e73\u7c73\u4f18\u60e0"],"average_price":"7800","cover_pic":"http:\/\/image1.ljcdn.com\/xf-resblock\/6a795907-0360-448d-9bfc-9971b4a5e11b.jpg.200x200.jpg","rooms":"3\u5c45\/2\u5c45","resblock_frame_area":"\u5efa\u9762 84~119m\u00b2","house_type":"\u666e\u901a\u4f4f\u5b85","url":"\/loupan\/p_jdjykaasmn\/","price_show_config":"1","show_price":"7800","show_price_unit":"\u5143\/\u5e73","show_price_desc":"\u5747\u4ef7"}],"5212025478262376":[{"district_id":"23008856","longitude":"121.352276","latitude":"37.548267","resblock_id":"5212025478262376","project_name":"jcxfaasmy","resblock_name":"\u5efa\u57ce\u897f\u5e9c","min_frame_area":"72","max_frame_area":"129","special_tags":["\u6bcf\u5e73\u7c73\u4f18\u60e0"],"average_price":"7800","cover_pic":"http:\/\/image1.ljcdn.com\/xf-resblock\/d4a7a411-e4b4-4a3b-abdb-e44caeb77ddb.jpg.200x200.jpg","rooms":"3\u5c45\/2\u5c45\/1\u5c45","resblock_frame_area":"\u5efa\u9762 72~129m\u00b2","house_type":"\u666e\u901a\u4f4f\u5b85","url":"\/loupan\/p_jcxfaasmy\/","price_show_config":"1","show_price":"7800","show_price_unit":"\u5143\/\u5e73","show_price_desc":"\u5747\u4ef7"}],"5212064803008605":[{"district_id":"23009087","longitude":"121.264169","latitude":"37.550695","resblock_id":"5212064803008605","project_name":"zwtaasrn","resblock_name":"\u6052\u5929\u7d2b\u5fae\u53f0","min_frame_area":"83","max_frame_area":"139","special_tags":["\u5168\u6b3e9.8\u6298  \u8d37\u6b3e9.9\u6298"],"average_price":"7800","cover_pic":"http:\/\/image1.ljcdn.com\/xf-resblock\/95f03b01-b96b-419c-8ce9-8fb0fa922fd1.jpg.200x200.jpg","rooms":"3\u5c45\/2\u5c45","resblock_frame_area":"\u5efa\u9762 83~139m\u00b2","house_type":"\u666e\u901a\u4f4f\u5b85","url":"\/loupan\/p_zwtaasrn\/","price_show_config":"1","show_price":"7800","show_price_unit":"\u5143\/\u5e73","show_price_desc":"\u5747\u4ef7"}],"5212064803009218":[{"district_id":"23009087","longitude":"121.256587","latitude":"37.567502","resblock_id":"5212064803009218","project_name":"ytxygcaassf","resblock_name":"\u661f\u9890\u5e7f\u573a","min_frame_area":"75","max_frame_area":"105","special_tags":[],"average_price":"7700","cover_pic":"http:\/\/image1.ljcdn.com\/xf-resblock\/61ee8469-efe9-4d8a-95f5-eb53c9930219.jpg.200x200.jpg","rooms":"3\u5c45\/2\u5c45","resblock_frame_area":"\u5efa\u9762 75~105m\u00b2","house_type":"\u666e\u901a\u4f4f\u5b85","url":"\/loupan\/p_ytxygcaassf\/","price_show_config":"1","show_price":"7700","show_price_unit":"\u5143\/\u5e73","show_price_desc":"\u5747\u4ef7"}],"5212041906827443":[{"district_id":"23008856","longitude":"121.366732","latitude":"37.489713","resblock_id":"5212041906827443","project_name":"tljynmpaasny","resblock_name":"\u5929\u4f26\u5609\u56ed\u67e0\u6aac\u6d3e","min_frame_area":"65","max_frame_area":"87","special_tags":[],"average_price":"7500","cover_pic":"http:\/\/image1.ljcdn.com\/xf-resblock\/9d4ea472-d419-4ce6-b3d5-fd6c27cf55fc.jpg.200x200.jpg","rooms":"2\u5c45","resblock_frame_area":"\u5efa\u9762 65~87m\u00b2","house_type":"\u666e\u901a\u4f4f\u5b85","url":"\/loupan\/p_tljynmpaasny\/","price_show_config":"1","show_price":"7500","show_price_unit":"\u5143\/\u5e73","show_price_desc":"\u5747\u4ef7"}],"5212154032106965":[{"district_id":"23009087","longitude":"121.149761","latitude":"37.606763","resblock_id":"5212154032106965","project_name":"zjyfyhaasrq","resblock_name":"\u4e2d\u5efa\u6d0b\u623f\u58f9\u53f7","min_frame_area":"163","max_frame_area":"287","special_tags":[],"average_price":"7500","cover_pic":"http:\/\/image1.ljcdn.com\/xf-resblock\/f3ff2fca-31dc-45fb-ad71-3861014abbfc.jpg.200x200.jpg","rooms":"5\u5c45\/4\u5c45","resblock_frame_area":"\u5efa\u9762 163~287m\u00b2","house_type":"\u666e\u901a\u4f4f\u5b85","url":"\/loupan\/p_zjyfyhaasrq\/","price_show_config":"1","show_price":"7500","show_price_unit":"\u5143\/\u5e73","show_price_desc":"\u5747\u4ef7"}],"5212064607449681":[{"district_id":"23009087","longitude":"121.149653","latitude":"37.60845","resblock_id":"5212064607449681","project_name":"zsmeblaaved","resblock_name":"\u62db\u5546\u9a6c\u5c14\u8d1d\u62c9","min_frame_area":"72","max_frame_area":"133","special_tags":["9.6\u6298"],"average_price":"7500","cover_pic":"http:\/\/image1.ljcdn.com\/xf-resblock\/a5f3478a-1c56-4aad-8ed9-a2a0bba345e3.jpg.200x200.jpg","rooms":"3\u5c45\/2\u5c45\/1\u5c45","resblock_frame_area":"\u5efa\u9762 72~133m\u00b2","house_type":"\u666e\u901a\u4f4f\u5b85","url":"\/loupan\/p_zsmeblaaved\/","price_show_config":"1","show_price":"7500","show_price_unit":"\u5143\/\u5e73","show_price_desc":"\u5747\u4ef7"}],"5211062389517":[{"district_id":"23008857","longitude":"121.26673108","latitude":"37.524137486126","resblock_id":"5211062389517","project_name":"aaspm","resblock_name":"\u5317\u65b9\u6708\u5149\u6021\u666f","min_frame_area":"84","max_frame_area":"107","special_tags":["\u5168\u6b3e9.7\u6298  \u8d37\u6b3e9.8\u6298"],"average_price":"7400","cover_pic":"http:\/\/image1.ljcdn.com\/xf-resblock\/9691e926-e75b-4cd5-bf41-a2cbbb51b711.jpg.200x200.jpg","rooms":"3\u5c45\/2\u5c45","resblock_frame_area":"\u5efa\u9762 84~107m\u00b2","house_type":"\u666e\u901a\u4f4f\u5b85","url":"\/loupan\/p_aaspm\/","price_show_config":"1","show_price":"7400","show_price_unit":"\u5143\/\u5e73","show_price_desc":"\u5747\u4ef7"}],"5211951223614589":[{"district_id":"23008856","longitude":"121.369787","latitude":"37.496893","resblock_id":"5211951223614589","project_name":"dxyyqasjaasmg","resblock_name":"\u5fb7\u99a8\u5712\u4e00\u671f\u7231\u4e0a\u5bb6","min_frame_area":"75","max_frame_area":"75","special_tags":["9.9\u6298"],"average_price":"7380","cover_pic":"http:\/\/image1.ljcdn.com\/xf-resblock\/7d016d26-69a8-4a7f-8c58-88b9f4ec2859.jpg.200x200.jpg","rooms":"2\u5c45","resblock_frame_area":"\u5efa\u9762 75m\u00b2","house_type":"\u666e\u901a\u4f4f\u5b85","url":"\/loupan\/p_dxyyqasjaasmg\/","price_show_config":"1","show_price":"7380","show_price_unit":"\u5143\/\u5e73","show_price_desc":"\u5747\u4ef7"}],"5211063003816":[{"district_id":"23008859","longitude":"121.45959140952","latitude":"37.453699236226","resblock_id":"5211063003816","project_name":"dhshthyyxaasrv","resblock_name":"\u5927\u534e\u4e0a\u6d77\u6ee9\u82b1\u56ed","min_frame_area":"78","max_frame_area":"78","special_tags":[],"average_price":"7300","cover_pic":"http:\/\/image1.ljcdn.com\/xf-resblock\/0f853507-24c1-4ed6-affd-3b7014d0fbc4.jpg.200x200.jpg","rooms":"2\u5c45","resblock_frame_area":"\u5efa\u9762 78m\u00b2","house_type":"\u666e\u901a\u4f4f\u5b85","url":"\/loupan\/p_dhshthyyxaasrv\/","price_show_config":"1","show_price":"7300","show_price_unit":"\u5143\/\u5e73","show_price_desc":"\u5747\u4ef7"}],"5212064271117891":[{"district_id":"23009087","longitude":"121.235639","latitude":"37.559078","resblock_id":"5212064271117891","project_name":"xcaasso","resblock_name":"\u9999\u6a59","min_frame_area":"84","max_frame_area":"137","special_tags":[],"average_price":"7300","cover_pic":"http:\/\/image1.ljcdn.com\/xf-resblock\/24898212-7e75-414e-b836-84a3991ce101.jpg.200x200.jpg","rooms":"3\u5c45\/2\u5c45","resblock_frame_area":"\u5efa\u9762 84~137m\u00b2","house_type":"\u666e\u901a\u4f4f\u5b85","url":"\/loupan\/p_xcaasso\/","price_show_config":"1","show_price":"7300","show_price_unit":"\u5143\/\u5e73","show_price_desc":"\u5747\u4ef7"}],"5211063040883":[{"district_id":"23008859","longitude":"121.47936406785","latitude":"37.455497749572","resblock_id":"5211063040883","project_name":"fdlcyxaaskl","resblock_name":"\u798f\u5730\u9686\u57ce","min_frame_area":"97","max_frame_area":"157","special_tags":["\u7acb\u51cf8000"],"average_price":"7200","cover_pic":"http:\/\/image1.ljcdn.com\/xf-resblock\/2f53bfd3-9362-446e-a2f1-5824793c8b56.jpg.200x200.jpg","rooms":"4\u5c45\/3\u5c45","resblock_frame_area":"\u5efa\u9762 97~157m\u00b2","house_type":"\u666e\u901a\u4f4f\u5b85","url":"\/loupan\/p_fdlcyxaaskl\/","price_show_config":"1","show_price":"7200","show_price_unit":"\u5143\/\u5e73","show_price_desc":"\u5747\u4ef7"}],"5212037478165647":[{"district_id":"23009088","longitude":"121.516013","latitude":"37.421048","resblock_id":"5212037478165647","project_name":"xsmscaasld","resblock_name":"\u5174\u76db\u94ed\u4ed5\u57ce","min_frame_area":"95","max_frame_area":"120","special_tags":["\u7acb\u51cf2\u4e07"],"average_price":"7200","cover_pic":"http:\/\/image1.ljcdn.com\/xf-resblock\/cbe9b94d-e215-40d8-8112-a6a69e62f47f.jpg.200x200.jpg","rooms":"3\u5c45\/2\u5c45","resblock_frame_area":"\u5efa\u9762 95~120m\u00b2","house_type":"\u666e\u901a\u4f4f\u5b85","url":"\/loupan\/p_xsmscaasld\/","price_show_config":"1","show_price":"7200","show_price_unit":"\u5143\/\u5e73","show_price_desc":"\u5747\u4ef7"}],"5212025478261975":[{"district_id":"23008856","longitude":"121.381412","latitude":"37.473337","resblock_id":"5212025478261975","project_name":"ljaasmu","resblock_name":"\u6717\u90e1","min_frame_area":"83","max_frame_area":"89","special_tags":["\u5168\u6b3e9\u6298  \u8d37\u6b3e9.2\u6298"],"average_price":"7200","cover_pic":"http:\/\/image1.ljcdn.com\/xf-resblock\/71f0b54a-fd16-4307-a919-a13b8dedee8c.jpg.200x200.jpg","rooms":"2\u5c45","resblock_frame_area":"\u5efa\u9762 83~89m\u00b2","house_type":"\u666e\u901a\u4f4f\u5b85","url":"\/loupan\/p_ljaasmu\/","price_show_config":"1","show_price":"7200","show_price_unit":"\u5143\/\u5e73","show_price_desc":"\u5747\u4ef7"}],"5211062478729":[{"district_id":"23009087","longitude":"121.183245","latitude":"37.588393","resblock_id":"5211062478729","project_name":"tmxcsqyxaasqm","resblock_name":"\u5929\u9a6c\u76f8\u57ce\u56db\u671f","min_frame_area":"99","max_frame_area":"143","special_tags":[],"average_price":"7200","cover_pic":"http:\/\/image1.ljcdn.com\/xf-resblock\/1679252e-95e1-4ef1-b329-059b65886b71.jpg.200x200.jpg","rooms":"3\u5c45\/2\u5c45","resblock_frame_area":"\u5efa\u9762 99~143m\u00b2","house_type":"\u666e\u901a\u4f4f\u5b85","url":"\/loupan\/p_tmxcsqyxaasqm\/","price_show_config":"1","show_price":"7200","show_price_unit":"\u5143\/\u5e73","show_price_desc":"\u5747\u4ef7"}],"5211063041935":[{"district_id":"23009088","longitude":"121.51702523577","latitude":"37.439199225074","resblock_id":"5211063041935","project_name":"rddhayxaasrz","resblock_name":"\u5bb9\u5927\u4e1c\u6d77\u5cb8","min_frame_area":"87","max_frame_area":"157","special_tags":[],"average_price":"7200","cover_pic":"http:\/\/image1.ljcdn.com\/xf-resblock\/168d82ee-ad31-460b-818e-b46e096afd88.jpg.200x200.jpg","rooms":"3\u5c45\/2\u5c45","resblock_frame_area":"\u5efa\u9762 87~157m\u00b2","house_type":"\u666e\u901a\u4f4f\u5b85","url":"\/loupan\/p_rddhayxaasrz\/","price_show_config":"1","show_price":"7200","show_price_unit":"\u5143\/\u5e73","show_price_desc":"\u5747\u4ef7"}],"5212065141175088":[{"district_id":"23009087","longitude":"121.225916","latitude":"37.568957","resblock_id":"5212065141175088","project_name":"xfjyaaziq","resblock_name":"\u5b66\u5e9c\u4f73\u82d1","min_frame_area":"83","max_frame_area":"112","special_tags":[],"average_price":"7100","cover_pic":"http:\/\/image1.ljcdn.com\/xf-resblock\/86404d83-99a3-4fcd-8c53-96775f548777.JPG.200x200.jpg","rooms":"3\u5c45\/2\u5c45","resblock_frame_area":"\u5efa\u9762 83~112m\u00b2","house_type":"\u666e\u901a\u4f4f\u5b85","url":"\/loupan\/p_xfjyaaziq\/","price_show_config":"1","show_price":"7100","show_price_unit":"\u5143\/\u5e73","show_price_desc":"\u5747\u4ef7"}],"5212043126322072":[{"district_id":"23008856","longitude":"121.359268","latitude":"37.473176","resblock_id":"5212043126322072","project_name":"hxgjgcaasoi","resblock_name":"\u7ea2\u661f\u56fd\u9645\u5e7f\u573a","min_frame_area":"76","max_frame_area":"76","special_tags":[],"average_price":"7000","cover_pic":"http:\/\/image1.ljcdn.com\/xf-resblock\/b4e1bc52-589c-4a36-b0bd-2595edc3e48d.jpg.200x200.jpg","rooms":"2\u5c45","resblock_frame_area":"\u5efa\u9762 76m\u00b2","house_type":"\u666e\u901a\u4f4f\u5b85","url":"\/loupan\/p_hxgjgcaasoi\/","price_show_config":"1","show_price":"7000","show_price_unit":"\u5143\/\u5e73","show_price_desc":"\u5747\u4ef7"}],"5211062287612":[{"district_id":"23008857","longitude":"121.27356031045","latitude":"37.516677411758","resblock_id":"5211062287612","project_name":"aasqg","resblock_name":"\u798f\u5229\u83b1\u5c0f\u533a","min_frame_area":"89","max_frame_area":"109","special_tags":["\u6bcf\u5e73\u7c73\u4f18\u60e0"],"average_price":"7000","cover_pic":"http:\/\/image1.ljcdn.com\/xf-resblock\/63e11a74-6c0e-4729-939b-51e1b28a2a3b.jpg.200x200.jpg","rooms":"3\u5c45\/2\u5c45","resblock_frame_area":"\u5efa\u9762 89~109m\u00b2","house_type":"\u666e\u901a\u4f4f\u5b85","url":"\/loupan\/p_aasqg\/","price_show_config":"1","show_price":"7000","show_price_unit":"\u5143\/\u5e73","show_price_desc":"\u5747\u4ef7"}],"5212065088482326":[{"district_id":"23009087","longitude":"121.250928","latitude":"37.547019","resblock_id":"5212065088482326","project_name":"tylcsqaasqn","resblock_name":"\u5929\u9890\u90e6\u57ce\u4e09\u671f","min_frame_area":"100","max_frame_area":"129","special_tags":[],"average_price":"6900","cover_pic":"http:\/\/image1.ljcdn.com\/xf-resblock\/e74c3d43-6d9c-432a-a092-e080ee24d7bd.jpg.200x200.jpg","rooms":"3\u5c45","resblock_frame_area":"\u5efa\u9762 100~129m\u00b2","house_type":"\u666e\u901a\u4f4f\u5b85","url":"\/loupan\/p_tylcsqaasqn\/","price_show_config":"1","show_price":"6900","show_price_unit":"\u5143\/\u5e73","show_price_desc":"\u5747\u4ef7"}],"5211062528402":[{"district_id":"23008856","longitude":"121.36468458936","latitude":"37.590078571824","resblock_id":"5211062528402","project_name":"hfkaasmq","resblock_name":"\u6d77\u5cf0","min_frame_area":"65","max_frame_area":"134","special_tags":["9.5\u6298"],"average_price":"6800","cover_pic":"http:\/\/image1.ljcdn.com\/xf-resblock\/6ce2408f-6008-46fa-9048-4bf0420ef088.jpg.200x200.jpg","rooms":"3\u5c45\/2\u5c45","resblock_frame_area":"\u5efa\u9762 65~134m\u00b2","house_type":"\u666e\u901a\u4f4f\u5b85","url":"\/loupan\/p_hfkaasmq\/","price_show_config":"1","show_price":"6800","show_price_unit":"\u5143\/\u5e73","show_price_desc":"\u5747\u4ef7"}],"5214186117082644":[{"district_id":"23009088","longitude":"121.496744","latitude":"37.459306","resblock_id":"5214186117082644","project_name":"htyzaavex","resblock_name":"\u6d77\u5929\u96c5\u7b51","min_frame_area":"123","max_frame_area":"197","special_tags":[],"average_price":"6800","cover_pic":"http:\/\/image1.ljcdn.com\/xf-resblock\/94f7f2c2-da04-4c78-8121-06e54f0751ab.jpg.200x200.jpg","rooms":"4\u5c45\/3\u5c45","resblock_frame_area":"\u5efa\u9762 123~197m\u00b2","house_type":"\u666e\u901a\u4f4f\u5b85","url":"\/loupan\/p_htyzaavex\/","price_show_config":"1","show_price":"6800","show_price_unit":"\u5143\/\u5e73","show_price_desc":"\u5747\u4ef7"}],"5211062476613":[{"district_id":"23009087","longitude":"121.17265363579","latitude":"37.588224464076","resblock_id":"5211062476613","project_name":"jhmddtaasqx","resblock_name":"\u91d1\u6cb3\u540d\u90fd","min_frame_area":"55","max_frame_area":"90","special_tags":["\u6bcf\u5e73\u7c73\u8865\u8d34"],"average_price":"6700","cover_pic":"http:\/\/image1.ljcdn.com\/xf-resblock\/fb077e92-a205-4d26-86d8-4c52a260615f.jpg.200x200.jpg","rooms":"2\u5c45\/1\u5c45","resblock_frame_area":"\u5efa\u9762 55~90m\u00b2","house_type":"\u666e\u901a\u4f4f\u5b85","url":"\/loupan\/p_jhmddtaasqx\/","price_show_config":"1","show_price":"6700","show_price_unit":"\u5143\/\u5e73","show_price_desc":"\u5747\u4ef7"}],"5211062635482":[{"district_id":"23008856","longitude":"121.35767323148","latitude":"37.48092198641","resblock_id":"5211062635482","project_name":"aasmv","resblock_name":"\u5c71\u8bed\u4e16\u5bb6","min_frame_area":0,"max_frame_area":0,"special_tags":[],"average_price":"6600","cover_pic":"http:\/\/image1.ljcdn.com\/xf-resblock\/35654170-fc78-4051-ac06-829a30265f12.jpg.200x200.jpg","rooms":null,"resblock_frame_area":"","house_type":"\u666e\u901a\u4f4f\u5b85","url":"\/loupan\/p_aasmv\/","price_show_config":"1","show_price":"6600","show_price_unit":"\u5143\/\u5e73","show_price_desc":"\u5747\u4ef7"}],"5211951900472302":[{"district_id":"23008856","longitude":"121.349144","latitude":"37.496471","resblock_id":"5211951900472302","project_name":"hlcycaasml","resblock_name":"\u6866\u6797\u5f69\u96f2\u57ce","min_frame_area":"68","max_frame_area":"86","special_tags":["\u5168\u6b3e9.8\u6298  \u8d37\u6b3e9.9\u6298"],"average_price":"6500","cover_pic":"http:\/\/image1.ljcdn.com\/xf-resblock\/8275b6b8-e639-46d6-938f-f02b10a2d16c.jpg.200x200.jpg","rooms":"2\u5c45","resblock_frame_area":"\u5efa\u9762 68~86m\u00b2","house_type":"\u666e\u901a\u4f4f\u5b85","url":"\/loupan\/p_hlcycaasml\/","price_show_config":"1","show_price":"6500","show_price_unit":"\u5143\/\u5e73","show_price_desc":"\u5747\u4ef7"}],"5212058419540291":[{"district_id":"23008857","longitude":"121.263355","latitude":"37.538817","resblock_id":"5212058419540291","project_name":"frfhmaasox","resblock_name":"\u798f\u745e\u798f\u6d77\u95e8","min_frame_area":"82","max_frame_area":"98","special_tags":["9.9\u6298"],"average_price":"6500","cover_pic":"http:\/\/image1.ljcdn.com\/xf-resblock\/8ac53ff9-6dee-405c-8a86-4308156d19cd.jpg.200x200.jpg","rooms":"3\u5c45\/2\u5c45","resblock_frame_area":"\u5efa\u9762 82~98m\u00b2","house_type":"\u666e\u901a\u4f4f\u5b85","url":"\/loupan\/p_frfhmaasox\/","price_show_config":"1","show_price":"6500","show_price_unit":"\u5143\/\u5e73","show_price_desc":"\u5747\u4ef7"}],"5211062310679":[{"district_id":"23008857","longitude":"121.26250241737","latitude":"37.491930831801","resblock_id":"5211062310679","project_name":"flygkaasqf","resblock_name":"\u5bcc\u4e3d\u9633\u5149","min_frame_area":"69","max_frame_area":"129","special_tags":[],"average_price":"6500","cover_pic":"http:\/\/image1.ljcdn.com\/xf-resblock\/a4705b90-4e8b-4591-913b-320292bf5878.jpg.200x200.jpg","rooms":"3\u5c45\/2\u5c45\/1\u5c45","resblock_frame_area":"\u5efa\u9762 69~129m\u00b2","house_type":"\u666e\u901a\u4f4f\u5b85","url":"\/loupan\/p_flygkaasqf\/","price_show_config":"1","show_price":"6500","show_price_unit":"\u5143\/\u5e73","show_price_desc":"\u5747\u4ef7"}],"5211062481769":[{"district_id":"23009087","longitude":"121.15136085137","latitude":"37.603902840708","resblock_id":"5211062481769","project_name":"zjyhhyyxaassh","resblock_name":"\u4e2d\u5efa\u60a6\u6d77\u548c\u56ed","min_frame_area":"102","max_frame_area":"120","special_tags":[],"average_price":"6500","cover_pic":"http:\/\/image1.ljcdn.com\/xf-resblock\/2e8851f8-e390-4666-83a6-aa2ed1b4f6f4.jpg.200x200.jpg","rooms":"4\u5c45\/3\u5c45\/2\u5c45","resblock_frame_area":"\u5efa\u9762 102~120m\u00b2","house_type":"\u666e\u901a\u4f4f\u5b85","url":"\/loupan\/p_zjyhhyyxaassh\/","price_show_config":"1","show_price":"6500","show_price_unit":"\u5143\/\u5e73","show_price_desc":"\u5747\u4ef7"}],"5211062752800":[{"district_id":"23008856","longitude":"121.3354306611","latitude":"37.521309989287","resblock_id":"5211062752800","project_name":"fcsjkaasnd","resblock_name":"\u5bcc\u6625\u5c71\u5c45","min_frame_area":"125","max_frame_area":"125","special_tags":[],"average_price":"6400","cover_pic":"http:\/\/image1.ljcdn.com\/xf-resblock\/df3c9d79-f53e-477e-8e0a-5674ddd2a912.jpg.200x200.jpg","rooms":"3\u5c45","resblock_frame_area":"\u5efa\u9762 125m\u00b2","house_type":"\u666e\u901a\u4f4f\u5b85","url":"\/loupan\/p_fcsjkaasnd\/","price_show_config":"1","show_price":"6400","show_price_unit":"\u5143\/\u5e73","show_price_desc":"\u5747\u4ef7"}],"5211062441782":[{"district_id":"23009087","longitude":"121.24723588329","latitude":"37.543540914345","resblock_id":"5211062441782","project_name":"hxtsjkaasrf","resblock_name":"\u6d77\u4fe1\u5929\u5c71\u90e1","min_frame_area":"86","max_frame_area":"106","special_tags":[],"average_price":"6300","cover_pic":"http:\/\/image1.ljcdn.com\/xf-resblock\/400f06aa-1e28-4cfa-8b82-b15fb7d1631c.jpg.200x200.jpg","rooms":"3\u5c45\/2\u5c45","resblock_frame_area":"\u5efa\u9762 86~106m\u00b2","house_type":"\u666e\u901a\u4f4f\u5b85","url":"\/loupan\/p_hxtsjkaasrf\/","price_show_config":"1","show_price":"6300","show_price_unit":"\u5143\/\u5e73","show_price_desc":"\u5747\u4ef7"}],"5211062427981":[{"district_id":"23009087","longitude":"121.21084010993","latitude":"37.565684361767","resblock_id":"5211062427981","project_name":"aasol","resblock_name":"\u5d5b\u666f\u534e\u57ce\u56db\u671f","min_frame_area":"74","max_frame_area":"115","special_tags":[],"average_price":"6200","cover_pic":"http:\/\/image1.ljcdn.com\/xf-resblock\/6d574c8d-7dec-4aa0-9380-a483958990ec.jpg.200x200.jpg","rooms":"3\u5c45\/2\u5c45","resblock_frame_area":"\u5efa\u9762 74~115m\u00b2","house_type":"\u666e\u901a\u4f4f\u5b85","url":"\/loupan\/p_aasol\/","price_show_config":"1","show_price":"6200","show_price_unit":"\u5143\/\u5e73","show_price_desc":"\u5747\u4ef7"}],"5212059797368933":[{"district_id":"23008857","longitude":"121.253276","latitude":"37.517117","resblock_id":"5212059797368933","project_name":"fdsyaaspg","resblock_name":"\u798f\u5730\u5c1a\u82d1","min_frame_area":"93","max_frame_area":"150","special_tags":["9.9\u6298"],"average_price":"6200","cover_pic":"http:\/\/image1.ljcdn.com\/xf-resblock\/577be49e-54c5-41b7-8716-8032840fc68a.jpg.200x200.jpg","rooms":"4\u5c45\/3\u5c45","resblock_frame_area":"\u5efa\u9762 93~150m\u00b2","house_type":"\u666e\u901a\u4f4f\u5b85","url":"\/loupan\/p_fdsyaaspg\/","price_show_config":"1","show_price":"6200","show_price_unit":"\u5143\/\u5e73","show_price_desc":"\u5747\u4ef7"}],"5212042314198174":[{"district_id":"23008858","longitude":"121.601236","latitude":"37.446267","resblock_id":"5212042314198174","project_name":"lhpthwaasyd","resblock_name":"\u9f99\u6e56\u5510\u5b81ONE","min_frame_area":"276","max_frame_area":"276","special_tags":[],"average_price":"6200","cover_pic":"http:\/\/image1.ljcdn.com\/xf-resblock\/2e998f2b-0ec8-459e-a459-0fcdc0f19d59.jpg.200x200.jpg","rooms":"4\u5c45","resblock_frame_area":"\u5efa\u9762 276m\u00b2","house_type":"\u666e\u901a\u4f4f\u5b85","url":"\/loupan\/p_lhpthwaasyd\/","price_show_config":"1","show_price":"6200","show_price_unit":"\u5143\/\u5e73","show_price_desc":"\u5747\u4ef7"}],"5211062310015":[{"district_id":"23008857","longitude":"121.26786918497","latitude":"37.507667357661","resblock_id":"5211062310015","project_name":"fhckaaspy","resblock_name":"\u798f\u6d77\u57ce","min_frame_area":"85","max_frame_area":"96","special_tags":[],"average_price":"6100","cover_pic":"http:\/\/image1.ljcdn.com\/xf-resblock\/bce3baf8-6e41-4104-98de-8f0560428c91.jpg.200x200.jpg","rooms":"2\u5c45","resblock_frame_area":"\u5efa\u9762 85~96m\u00b2","house_type":"\u666e\u901a\u4f4f\u5b85","url":"\/loupan\/p_fhckaaspy\/","price_show_config":"1","show_price":"6100","show_price_unit":"\u5143\/\u5e73","show_price_desc":"\u5747\u4ef7"}],"5212037388775547":[{"district_id":"23008856","longitude":"121.361865","latitude":"37.45218","resblock_id":"5212037388775547","project_name":"ycssaasnf","resblock_name":"\u9038\u57ce\u5c71\u8272","min_frame_area":"78","max_frame_area":"93","special_tags":["9.7\u6298"],"average_price":"6000","cover_pic":"http:\/\/image1.ljcdn.com\/xf-resblock\/8ceedde8-ee5b-4c33-9294-37fd35a03d20.jpg.200x200.jpg","rooms":"3\u5c45\/2\u5c45","resblock_frame_area":"\u5efa\u9762 78~93m\u00b2","house_type":"\u666e\u901a\u4f4f\u5b85","url":"\/loupan\/p_ycssaasnf\/","price_show_config":"1","show_price":"6000","show_price_unit":"\u5143\/\u5e73","show_price_desc":"\u5747\u4ef7"}],"5212042314198371":[{"district_id":"23008856","longitude":"121.361036","latitude":"37.449151","resblock_id":"5212042314198371","project_name":"atbaasoc","resblock_name":"\u7231\u6c40\u5821","min_frame_area":"59","max_frame_area":"102","special_tags":["\u6bcf\u5e73\u7c73\u4f18\u60e0"],"average_price":"6000","cover_pic":"http:\/\/image1.ljcdn.com\/xf-resblock\/39ba4fe9-f070-44cb-b057-d30907df6498.jpg.200x200.jpg","rooms":"3\u5c45\/2\u5c45\/1\u5c45","resblock_frame_area":"\u5efa\u9762 59~102m\u00b2","house_type":"\u666e\u901a\u4f4f\u5b85","url":"\/loupan\/p_atbaasoc\/","price_show_config":"1","show_price":"6000","show_price_unit":"\u5143\/\u5e73","show_price_desc":"\u5747\u4ef7"}],"5212047800873569":[{"district_id":"23008857","longitude":"121.266886","latitude":"37.5114","resblock_id":"5212047800873569","project_name":"yzgcaasov","resblock_name":"\u94f6\u5ea7\u5e7f\u573a","min_frame_area":"73","max_frame_area":"112","special_tags":["\u7acb\u51cf4000"],"average_price":"6000","cover_pic":"http:\/\/image1.ljcdn.com\/xf-resblock\/56307d8b-783a-4efa-878f-1913df1fa1ae.jpg.200x200.jpg","rooms":"3\u5c45\/2\u5c45","resblock_frame_area":"\u5efa\u9762 73~112m\u00b2","house_type":"\u666e\u901a\u4f4f\u5b85","url":"\/loupan\/p_yzgcaasov\/","price_show_config":"1","show_price":"6000","show_price_unit":"\u5143\/\u5e73","show_price_desc":"\u5747\u4ef7"}],"5212058896380874":[{"district_id":"23008857","longitude":"121.28522","latitude":"37.532551","resblock_id":"5212058896380874","project_name":"tysjyaaspa","resblock_name":"\u5929\u4e1a\u00b7\u76db\u4e16\u666f\u82d1","min_frame_area":"66","max_frame_area":"101","special_tags":["\u6bcf\u5e73\u7c73\u4f18\u60e0"],"average_price":"6000","cover_pic":"http:\/\/image1.ljcdn.com\/xf-resblock\/7f1bf0e1-02b0-4156-ac59-6624b9b4f0c8.jpg.200x200.jpg","rooms":"3\u5c45\/2\u5c45","resblock_frame_area":"\u5efa\u9762 66~101m\u00b2","house_type":"\u666e\u901a\u4f4f\u5b85","url":"\/loupan\/p_tysjyaaspa\/","price_show_config":"1","show_price":"6000","show_price_unit":"\u5143\/\u5e73","show_price_desc":"\u5747\u4ef7"}],"5212064607449594":[{"district_id":"23009087","longitude":"121.202617","latitude":"37.55297","resblock_id":"5212064607449594","project_name":"hxyyxzaasrp","resblock_name":"\u6d77\u4fe1\u4f9d\u4e91\u5c0f\u9547","min_frame_area":"100","max_frame_area":"145","special_tags":["\u7acb\u51cf5000"],"average_price":"6000","cover_pic":"http:\/\/image1.ljcdn.com\/xf-resblock\/587af57d-16f3-4df2-8659-3fcc9b6ec5a3.jpg.200x200.jpg","rooms":"3\u5c45\/2\u5c45","resblock_frame_area":"\u5efa\u9762 100~145m\u00b2","house_type":"\u666e\u901a\u4f4f\u5b85","url":"\/loupan\/p_hxyyxzaasrp\/","price_show_config":"1","show_price":"6000","show_price_unit":"\u5143\/\u5e73","show_price_desc":"\u5747\u4ef7"}],"5212059336520604":[{"district_id":"23008858","longitude":"121.590006","latitude":"37.397816","resblock_id":"5212059336520604","project_name":"yxypyfaasts","resblock_name":"\u610f\u7965\u4e00\u54c1\u6d0b\u623f","min_frame_area":"127","max_frame_area":"127","special_tags":["\u6bcf\u5e73\u7c73\u4f18\u60e0"],"average_price":"6000","cover_pic":"http:\/\/image1.ljcdn.com\/xf-resblock\/f9eaa468-5f37-4386-8805-277fab566e86.jpg.200x200.jpg","rooms":"3\u5c45","resblock_frame_area":"\u5efa\u9762 127m\u00b2","house_type":"\u666e\u901a\u4f4f\u5b85","url":"\/loupan\/p_yxypyfaasts\/","price_show_config":"1","show_price":"6000","show_price_unit":"\u5143\/\u5e73","show_price_desc":"\u5747\u4ef7"}],"5212047800873289":[{"district_id":"23008858","longitude":"121.613245","latitude":"37.437783","resblock_id":"5212047800873289","project_name":"rkehaasvn","resblock_name":"\u878d\u521b\u8fe9\u6d77","min_frame_area":"85","max_frame_area":"174","special_tags":[],"average_price":"6000","cover_pic":"http:\/\/image1.ljcdn.com\/xf-resblock\/bbb3e0f0-ce78-42c3-ab58-911c0e8eccfe.jpg.200x200.jpg","rooms":"4\u5c45\/3\u5c45\/2\u5c45","resblock_frame_area":"\u5efa\u9762 85~174m\u00b2","house_type":"\u666e\u901a\u4f4f\u5b85","url":"\/loupan\/p_rkehaasvn\/","price_show_config":"1","show_price":"6000","show_price_unit":"\u5143\/\u5e73","show_price_desc":"\u5747\u4ef7"}],"5212058419540507":[{"district_id":"23008858","longitude":"121.652915","latitude":"37.451507","resblock_id":"5212058419540507","project_name":"zyqhysaawdh","resblock_name":"\u4e2d\u51b6\u6c81\u6d77\u4e91\u5885","min_frame_area":"83","max_frame_area":"119","special_tags":[],"average_price":"6000","cover_pic":"http:\/\/image1.ljcdn.com\/xf-resblock\/8d57497e-c24d-4d45-ba8d-119c05378026.jpg.200x200.jpg","rooms":"3\u5c45\/2\u5c45","resblock_frame_area":"\u5efa\u9762 83~119m\u00b2","house_type":"\u666e\u901a\u4f4f\u5b85","url":"\/loupan\/p_zyqhysaawdh\/","price_show_config":"1","show_price":"6000","show_price_unit":"\u5143\/\u5e73","show_price_desc":"\u5747\u4ef7"}],"5211952454118494":[{"district_id":"23008856","longitude":"121.363655","latitude":"37.466881","resblock_id":"5211952454118494","project_name":"xbxzzyfaawjx","resblock_name":"\u9999\u69df\u5c0f\u9547\u72b6\u5143\u5e9c","min_frame_area":"73","max_frame_area":"86","special_tags":[],"average_price":"6000","cover_pic":"http:\/\/image1.ljcdn.com\/xf-resblock\/df1e987e-ec86-4344-9974-28902723b2c2.jpg.200x200.jpg","rooms":"3\u5c45\/2\u5c45","resblock_frame_area":"\u5efa\u9762 73~86m\u00b2","house_type":"\u666e\u901a\u4f4f\u5b85","url":"\/loupan\/p_xbxzzyfaawjx\/","price_show_config":"1","show_price":"6000","show_price_unit":"\u5143\/\u5e73","show_price_desc":"\u5747\u4ef7"}],"5212024341607147":[{"district_id":"23008856","longitude":"121.325159","latitude":"37.526083","resblock_id":"5212024341607147","project_name":"zhmdaasmx","resblock_name":"\u829d\u534e\u540d\u7b2c","min_frame_area":"78","max_frame_area":"108","special_tags":["\u5bb6\u7535\u793c"],"average_price":"5900","cover_pic":"http:\/\/image1.ljcdn.com\/xf-resblock\/028932a0-0376-444b-816b-cf38d279565f.jpg.200x200.jpg","rooms":"3\u5c45\/2\u5c45","resblock_frame_area":"\u5efa\u9762 78~108m\u00b2","house_type":"\u666e\u901a\u4f4f\u5b85","url":"\/loupan\/p_zhmdaasmx\/","price_show_config":"1","show_price":"5900","show_price_unit":"\u5143\/\u5e73","show_price_desc":"\u5747\u4ef7"}],"5211062762924":[{"district_id":"23008856","longitude":"121.32165510185","latitude":"37.542585092545","resblock_id":"5211062762924","project_name":"csxdcyxaasnu","resblock_name":"\u695a\u76db\u73b0\u4ee3\u57ce","min_frame_area":"46","max_frame_area":"118","special_tags":["\u6bcf\u5e73\u7c73\u4f18\u60e0"],"average_price":"5800","cover_pic":"http:\/\/image1.ljcdn.com\/xf-resblock\/78e7b847-6713-4353-9ad8-0e7def77b9bd.jpg.200x200.jpg","rooms":"3\u5c45\/2\u5c45\/1\u5c45","resblock_frame_area":"\u5efa\u9762 46~118m\u00b2","house_type":"\u666e\u901a\u4f4f\u5b85","url":"\/loupan\/p_csxdcyxaasnu\/","price_show_config":"1","show_price":"5800","show_price_unit":"\u5143\/\u5e73","show_price_desc":"\u5747\u4ef7"}],"5212041334566660":[{"district_id":"23008856","longitude":"121.338328","latitude":"37.535484","resblock_id":"5212041334566660","project_name":"hljyaasnw","resblock_name":"\u534e\u4e50\u5bb6\u56ed","min_frame_area":"86","max_frame_area":"134","special_tags":[],"average_price":"5800","cover_pic":"http:\/\/image1.ljcdn.com\/xf-resblock\/118ded69-98d6-4f9e-b465-dc92257992f3.jpg.200x200.jpg","rooms":"4\u5c45\/3\u5c45","resblock_frame_area":"\u5efa\u9762 86~134m\u00b2","house_type":"\u666e\u901a\u4f4f\u5b85","url":"\/loupan\/p_hljyaasnw\/","price_show_config":"1","show_price":"5800","show_price_unit":"\u5143\/\u5e73","show_price_desc":"\u5747\u4ef7"}],"5211062480830":[{"district_id":"23009087","longitude":"121.16383955117","latitude":"37.5942072714","resblock_id":"5211062480830","project_name":"yxxhjskaasod","resblock_name":"\u8d8a\u79c0\u661f\u6c47\u91d1\u6c99","min_frame_area":"75","max_frame_area":"109","special_tags":[],"average_price":"5800","cover_pic":"http:\/\/image1.ljcdn.com\/xf-resblock\/62970470-55cc-45ba-9035-3c276819970e.jpg.200x200.jpg","rooms":"4\u5c45\/3\u5c45\/2\u5c45","resblock_frame_area":"\u5efa\u9762 75~109m\u00b2","house_type":"\u666e\u901a\u4f4f\u5b85","url":"\/loupan\/p_yxxhjskaasod\/","price_show_config":"1","show_price":"5800","show_price_unit":"\u5143\/\u5e73","show_price_desc":"\u5747\u4ef7"}],"5218061965930637":[{"district_id":"23008860","longitude":"120.401054","latitude":"37.712073","resblock_id":"5218061965930637","project_name":"lhsjdeqabahu","resblock_name":"\u9886\u6d77\u4e16\u754c\u5c9b\u4e8c\u671f","min_frame_area":"75","max_frame_area":"75","special_tags":[],"average_price":"5800","cover_pic":"http:\/\/image1.ljcdn.com\/xf-resblock\/efc02c62-7b59-4dff-ba30-4ce5b240de6e.jpg.200x200.jpg","rooms":"2\u5c45","resblock_frame_area":"\u5efa\u9762 75m\u00b2","house_type":"\u666e\u901a\u4f4f\u5b85","url":"\/loupan\/p_lhsjdeqabahu\/","price_show_config":"1","show_price":"5800","show_price_unit":"\u5143\/\u5e73","show_price_desc":"\u5747\u4ef7"}],"5212059989258053":[{"district_id":"23008857","longitude":"121.263733","latitude":"37.495111","resblock_id":"5212059989258053","project_name":"yxhtaaspk","resblock_name":"\u6021\u99a8\u534e\u5ead","min_frame_area":"71","max_frame_area":"128","special_tags":["8.5\u6298"],"average_price":"5700","cover_pic":"http:\/\/image1.ljcdn.com\/xf-resblock\/35cf6abb-67f3-40d4-a173-1471520423c9.jpg.200x200.jpg","rooms":"4\u5c45\/3\u5c45\/2\u5c45","resblock_frame_area":"\u5efa\u9762 71~128m\u00b2","house_type":"\u666e\u901a\u4f4f\u5b85","url":"\/loupan\/p_yxhtaaspk\/","price_show_config":"1","show_price":"5700","show_price_unit":"\u5143\/\u5e73","show_price_desc":"\u5747\u4ef7"}],"5211062414174":[{"district_id":"23008857","longitude":"121.23918480441","latitude":"37.525356982124","resblock_id":"5211062414174","project_name":"wkjrfjkaastw","resblock_name":"\u4e07\u79d1\u5047\u65e5\u98ce\u666f","min_frame_area":"75","max_frame_area":"105","special_tags":[],"average_price":"5700","cover_pic":"http:\/\/image1.ljcdn.com\/xf-resblock\/f3311e4b-bf22-435b-822d-ad1b9600ff01.jpg.200x200.jpg","rooms":"3\u5c45\/2\u5c45","resblock_frame_area":"\u5efa\u9762 75~105m\u00b2","house_type":"\u666e\u901a\u4f4f\u5b85","url":"\/loupan\/p_wkjrfjkaastw\/","price_show_config":"1","show_price":"5700","show_price_unit":"\u5143\/\u5e73","show_price_desc":"\u5747\u4ef7"}],"5212042103435136":[{"district_id":"23008858","longitude":"121.586081","latitude":"37.435434","resblock_id":"5212042103435136","project_name":"flzjszaasyf","resblock_name":"\u5bcc\u4e3d\u7d2b\u91d1\u5c71\u5e84","min_frame_area":"140","max_frame_area":"140","special_tags":["\u5168\u6b3e9.9\u6298"],"average_price":"5700","cover_pic":"http:\/\/image1.ljcdn.com\/xf-resblock\/6bdef7a2-e24e-4214-b742-8d2d2fd35b8e.jpg.200x200.jpg","rooms":"3\u5c45","resblock_frame_area":"\u5efa\u9762 140m\u00b2","house_type":"\u666e\u901a\u4f4f\u5b85","url":"\/loupan\/p_flzjszaasyf\/","price_show_config":"1","show_price":"5700","show_price_unit":"\u5143\/\u5e73","show_price_desc":"\u5747\u4ef7"}],"5212729626931076":[{"district_id":"23009087","longitude":"121.181915","latitude":"37.567812","resblock_id":"5212729626931076","project_name":"jcxcaavzb","resblock_name":"\u805a\u521b\u65b0\u57ce","min_frame_area":"73","max_frame_area":"107","special_tags":[],"average_price":"5700","cover_pic":"http:\/\/image1.ljcdn.com\/xf-resblock\/968df4af-0e67-40fe-b46a-91ae5f9c517c.jpg.200x200.jpg","rooms":"3\u5c45\/2\u5c45","resblock_frame_area":"\u5efa\u9762 73~107m\u00b2","house_type":"\u666e\u901a\u4f4f\u5b85","url":"\/loupan\/p_jcxcaavzb\/","price_show_config":"1","show_price":"5700","show_price_unit":"\u5143\/\u5e73","show_price_desc":"\u5747\u4ef7"}],"5212047205281610":[{"district_id":"23008857","longitude":"121.275141","latitude":"37.531549","resblock_id":"5212047205281610","project_name":"dygjxqaasot","resblock_name":"\u7b2c\u4e00\u56fd\u9645\u65b0\u533a","min_frame_area":"67","max_frame_area":"108","special_tags":["9.8\u6298"],"average_price":"5600","cover_pic":"http:\/\/image1.ljcdn.com\/xf-resblock\/1230590c-a92f-44ea-b2a4-758c341ff690.jpg.200x200.jpg","rooms":"3\u5c45\/2\u5c45","resblock_frame_area":"\u5efa\u9762 67~108m\u00b2","house_type":"\u666e\u901a\u4f4f\u5b85","url":"\/loupan\/p_dygjxqaasot\/","price_show_config":"1","show_price":"5600","show_price_unit":"\u5143\/\u5e73","show_price_desc":"\u5747\u4ef7"}],"5212062371360301":[{"district_id":"23008857","longitude":"121.244671","latitude":"37.502511","resblock_id":"5212062371360301","project_name":"qdyfaaspp","resblock_name":"\u4e03\u680b\u6d0b\u623f","min_frame_area":"73","max_frame_area":"84","special_tags":["\u6bcf\u5e73\u7c73\u4f18\u60e0"],"average_price":"5600","cover_pic":"http:\/\/image1.ljcdn.com\/xf-resblock\/49f594c6-2208-418d-8fcc-c7189da10192.jpg.200x200.jpg","rooms":"2\u5c45","resblock_frame_area":"\u5efa\u9762 73~84m\u00b2","house_type":"\u666e\u901a\u4f4f\u5b85","url":"\/loupan\/p_qdyfaaspp\/","price_show_config":"1","show_price":"5600","show_price_unit":"\u5143\/\u5e73","show_price_desc":"\u5747\u4ef7"}],"5212057791966715":[{"district_id":"23008858","longitude":"121.614755","latitude":"37.434975","resblock_id":"5212057791966715","project_name":"hbkcaasue","resblock_name":"\u77f3\u836f\u5065\u5eb7\u57ce","min_frame_area":"51","max_frame_area":"103","special_tags":["9.3\u6298"],"average_price":"5600","cover_pic":"http:\/\/image1.ljcdn.com\/xf-resblock\/f863cba2-71a4-477f-aea0-5e6482b38825.jpg.200x200.jpg","rooms":"3\u5c45\/2\u5c45\/1\u5c45","resblock_frame_area":"\u5efa\u9762 51~103m\u00b2","house_type":"\u666e\u901a\u4f4f\u5b85","url":"\/loupan\/p_hbkcaasue\/","price_show_config":"1","show_price":"5600","show_price_unit":"\u5143\/\u5e73","show_price_desc":"\u5747\u4ef7"}],"5212057791966632":[{"district_id":"23008858","longitude":"121.629343","latitude":"37.443284","resblock_id":"5212057791966632","project_name":"txmyaasuj","resblock_name":"\u5929\u7fd4\u8317\u82d1","min_frame_area":"77","max_frame_area":"133","special_tags":[],"average_price":"5600","cover_pic":"http:\/\/image1.ljcdn.com\/xf-resblock\/5c83679a-7424-4bb2-8245-5e77cea2bd89.jpg.200x200.jpg","rooms":"3\u5c45\/2\u5c45\/1\u5c45","resblock_frame_area":"\u5efa\u9762 77~133m\u00b2","house_type":"\u666e\u901a\u4f4f\u5b85","url":"\/loupan\/p_txmyaasuj\/","price_show_config":"1","show_price":"5600","show_price_unit":"\u5143\/\u5e73","show_price_desc":"\u5747\u4ef7"}],"5212059625140542":[{"district_id":"23008857","longitude":"121.259969","latitude":"37.521976","resblock_id":"5212059625140542","project_name":"mgyaaspf","resblock_name":"\u73ab\u7470\u56ed","min_frame_area":"60","max_frame_area":"75","special_tags":[],"average_price":"5500","cover_pic":"http:\/\/image1.ljcdn.com\/xf-resblock\/bbba3198-0e15-488c-9d13-0871ed147d35.jpg.200x200.jpg","rooms":"2\u5c45","resblock_frame_area":"\u5efa\u9762 60~75m\u00b2","house_type":"\u666e\u901a\u4f4f\u5b85","url":"\/loupan\/p_mgyaaspf\/","price_show_config":"1","show_price":"5500","show_price_unit":"\u5143\/\u5e73","show_price_desc":"\u5747\u4ef7"}],"5211062292343":[{"district_id":"23008857","longitude":"121.25919311562","latitude":"37.496909451734","resblock_id":"5211062292343","project_name":"aaspt","resblock_name":"\u4f73\u5b89\u82b1\u56ed","min_frame_area":"64","max_frame_area":"88","special_tags":["\u8d2d\u623f\u8865\u8d34"],"average_price":"5500","cover_pic":"http:\/\/image1.ljcdn.com\/xf-resblock\/dc90d0f9-6101-4a8b-9b6c-b7a91c29ce57.jpg.200x200.jpg","rooms":"3\u5c45\/2\u5c45","resblock_frame_area":"\u5efa\u9762 64~88m\u00b2","house_type":"\u666e\u901a\u4f4f\u5b85","url":"\/loupan\/p_aaspt\/","price_show_config":"1","show_price":"5500","show_price_unit":"\u5143\/\u5e73","show_price_desc":"\u5747\u4ef7"}],"5212057791966447":[{"district_id":"23008858","longitude":"121.782271","latitude":"37.338347","resblock_id":"5212057791966447","project_name":"lqyfaasum","resblock_name":"\u9f99\u6cc9\u5fa1\u5e9c","min_frame_area":"63","max_frame_area":"84","special_tags":["\u5168\u6b3e9.8\u6298  \u8d37\u6b3e9.9\u6298"],"average_price":"5500","cover_pic":"http:\/\/image1.ljcdn.com\/xf-resblock\/b3ba6b13-daef-4d62-b9bb-046716bc4d7d.jpg.200x200.jpg","rooms":"3\u5c45\/2\u5c45\/1\u5c45","resblock_frame_area":"\u5efa\u9762 63~84m\u00b2","house_type":"\u666e\u901a\u4f4f\u5b85","url":"\/loupan\/p_lqyfaasum\/","price_show_config":"1","show_price":"5500","show_price_unit":"\u5143\/\u5e73","show_price_desc":"\u5747\u4ef7"}],"5212024341606745":[{"district_id":"23008856","longitude":"121.335728","latitude":"37.525243","resblock_id":"5212024341606745","project_name":"cyyjaasmr","resblock_name":"\u8fb0\u6e90\u96c5\u666f","min_frame_area":"72","max_frame_area":"101","special_tags":[],"average_price":"5400","cover_pic":"http:\/\/image1.ljcdn.com\/xf-resblock\/b8467a48-cfae-4b8f-bc86-27ca5c941250.jpg.200x200.jpg","rooms":"3\u5c45\/2\u5c45","resblock_frame_area":"\u5efa\u9762 72~101m\u00b2","house_type":"\u666e\u901a\u4f4f\u5b85","url":"\/loupan\/p_cyyjaasmr\/","price_show_config":"1","show_price":"5400","show_price_unit":"\u5143\/\u5e73","show_price_desc":"\u5747\u4ef7"}],"5211062292102":[{"district_id":"23008857","longitude":"121.26107863298","latitude":"37.511113816011","resblock_id":"5211062292102","project_name":"aaspc","resblock_name":"\u6fb3\u57ce\u82d1","min_frame_area":"72","max_frame_area":"107","special_tags":[],"average_price":"5400","cover_pic":"http:\/\/image1.ljcdn.com\/xf-resblock\/c62d454a-110b-44a9-b142-13664b571cab.jpg.200x200.jpg","rooms":"3\u5c45\/2\u5c45","resblock_frame_area":"\u5efa\u9762 72~107m\u00b2","house_type":"\u666e\u901a\u4f4f\u5b85","url":"\/loupan\/p_aaspc\/","price_show_config":"1","show_price":"5400","show_price_unit":"\u5143\/\u5e73","show_price_desc":"\u5747\u4ef7"}],"5212047205281617":[{"district_id":"23008857","longitude":"121.260306","latitude":"37.51871","resblock_id":"5212047205281617","project_name":"hdggaassv","resblock_name":"\u8c6a\u5fb7\u516c\u9986","min_frame_area":"83","max_frame_area":"101","special_tags":["\u6bcf\u5e73\u7c73\u4f18\u60e0"],"average_price":"5400","cover_pic":"http:\/\/image1.ljcdn.com\/xf-resblock\/432cdb04-c462-4110-b32c-63ca54d5812c.jpg.200x200.jpg","rooms":"3\u5c45\/2\u5c45","resblock_frame_area":"\u5efa\u9762 83~101m\u00b2","house_type":"\u666e\u901a\u4f4f\u5b85","url":"\/loupan\/p_hdggaassv\/","price_show_config":"1","show_price":"5400","show_price_unit":"\u5143\/\u5e73","show_price_desc":"\u5747\u4ef7"}],"5214172002988680":[{"district_id":"23008858","longitude":"121.625067","latitude":"37.443428","resblock_id":"5214172002988680","project_name":"hyxlhaaawba","resblock_name":"\u534e\u5cb3\u897f\u4e3d\u6d77\u5cb8","min_frame_area":"88","max_frame_area":"160","special_tags":["\u5168\u6b3e9.9\u6298  \u8d37\u6b3e9.8\u6298"],"average_price":"5400","cover_pic":"http:\/\/image1.ljcdn.com\/xf-resblock\/995e1ef5-f7c1-45f7-b32d-dfde3c0b5ec2.jpg.200x200.jpg","rooms":"3\u5c45\/2\u5c45","resblock_frame_area":"\u5efa\u9762 88~160m\u00b2","house_type":"\u666e\u901a\u4f4f\u5b85","url":"\/loupan\/p_hyxlhaaawba\/","price_show_config":"1","show_price":"5400","show_price_unit":"\u5143\/\u5e73","show_price_desc":"\u5747\u4ef7"}],"5218061409660426":[{"district_id":"23008860","longitude":"120.438837","latitude":"37.6438","resblock_id":"5218061409660426","project_name":"whydabaid","resblock_name":"\u4e07\u8c6a\u4f0a\u987f","min_frame_area":"84","max_frame_area":"84","special_tags":[],"average_price":"5400","cover_pic":"http:\/\/image1.ljcdn.com\/xf-resblock\/7cd43d8c-d602-4bff-9f1f-7b284f3e6958.jpg.200x200.jpg","rooms":"2\u5c45","resblock_frame_area":"\u5efa\u9762 84m\u00b2","house_type":"\u666e\u901a\u4f4f\u5b85","url":"\/loupan\/p_whydabaid\/","price_show_config":"1","show_price":"5400","show_price_unit":"\u5143\/\u5e73","show_price_desc":"\u5747\u4ef7"}],"5212063420460876":[{"district_id":"23008858","longitude":"121.603544","latitude":"37.41159","resblock_id":"5212063420460876","project_name":"thxcaasmb","resblock_name":"\u5929\u548c\u65b0\u57ce","min_frame_area":"149","max_frame_area":"149","special_tags":["\u6bcf\u5e73\u7c73\u4f18\u60e0"],"average_price":"5300","cover_pic":"http:\/\/image1.ljcdn.com\/xf-resblock\/07d96f2a-6ef0-493f-98f4-060529f7c43d.jpg.200x200.jpg","rooms":"3\u5c45","resblock_frame_area":"\u5efa\u9762 149m\u00b2","house_type":"\u666e\u901a\u4f4f\u5b85","url":"\/loupan\/p_thxcaasmb\/","price_show_config":"1","show_price":"5300","show_price_unit":"\u5143\/\u5e73","show_price_desc":"\u5747\u4ef7"}],"5212039895134443":[{"district_id":"23008856","longitude":"121.303833","latitude":"37.549132","resblock_id":"5212039895134443","project_name":"xmchyxaasnj","resblock_name":"\u73ba\u840c\u957f\u6cb3\u5370\u8c61","min_frame_area":"63","max_frame_area":"94","special_tags":["\u5168\u6b3e9.5\u6298  \u8d37\u6b3e9.7\u6298"],"average_price":"5300","cover_pic":"http:\/\/image1.ljcdn.com\/xf-resblock\/bd7de0c5-7796-410c-8d27-7ec49e1163d1.jpg.200x200.jpg","rooms":"3\u5c45\/2\u5c45","resblock_frame_area":"\u5efa\u9762 63~94m\u00b2","house_type":"\u666e\u901a\u4f4f\u5b85","url":"\/loupan\/p_xmchyxaasnj\/","price_show_config":"1","show_price":"5300","show_price_unit":"\u5143\/\u5e73","show_price_desc":"\u5747\u4ef7"}],"5211062476858":[{"district_id":"23009087","longitude":"121.17019064529","latitude":"37.592347959071","resblock_id":"5211062476858","project_name":"jqphwkaasog","resblock_name":"\u91d1\u6865\u6f8e\u6e56\u6e7e","min_frame_area":"74","max_frame_area":"101","special_tags":[],"average_price":"5300","cover_pic":"http:\/\/image1.ljcdn.com\/xf-resblock\/a2652f1c-df36-4e62-9db3-86ee5da4470d.jpg.200x200.jpg","rooms":"3\u5c45\/2\u5c45","resblock_frame_area":"\u5efa\u9762 74~101m\u00b2","house_type":"\u666e\u901a\u4f4f\u5b85","url":"\/loupan\/p_jqphwkaasog\/","price_show_config":"1","show_price":"5300","show_price_unit":"\u5143\/\u5e73","show_price_desc":"\u5747\u4ef7"}],"5212058896380471":[{"district_id":"23008857","longitude":"121.263625","latitude":"37.524566","resblock_id":"5212058896380471","project_name":"xtxaaasoy","resblock_name":"\u9999\u7f07\u7199\u5cb8","min_frame_area":"76","max_frame_area":"104","special_tags":["8.9\u6298"],"average_price":"5300","cover_pic":"http:\/\/image1.ljcdn.com\/xf-resblock\/5c4aad66-4c61-4432-95ce-060ca6935df1.jpg.200x200.jpg","rooms":"3\u5c45\/2\u5c45","resblock_frame_area":"\u5efa\u9762 76~104m\u00b2","house_type":"\u666e\u901a\u4f4f\u5b85","url":"\/loupan\/p_xtxaaasoy\/","price_show_config":"1","show_price":"5300","show_price_unit":"\u5143\/\u5e73","show_price_desc":"\u5747\u4ef7"}],"5212059452910832":[{"district_id":"23008857","longitude":"121.278106","latitude":"37.530075","resblock_id":"5212059452910832","project_name":"byfaaspe","resblock_name":"\u94c2\u60a6\u5e9c","min_frame_area":"77","max_frame_area":"77","special_tags":["\u6625\u5b63\u65c5\u6e38\u57fa\u91d1"],"average_price":"5300","cover_pic":"http:\/\/image1.ljcdn.com\/xf-resblock\/ef5502b0-4986-427d-9fc0-44b7a0d8988f.jpg.200x200.jpg","rooms":"2\u5c45","resblock_frame_area":"\u5efa\u9762 77m\u00b2","house_type":"\u666e\u901a\u4f4f\u5b85","url":"\/loupan\/p_byfaaspe\/","price_show_config":"1","show_price":"5300","show_price_unit":"\u5143\/\u5e73","show_price_desc":"\u5747\u4ef7"}],"5211063135265":[{"district_id":"23009088","longitude":"121.571546","latitude":"37.4171","resblock_id":"5211063135265","project_name":"gzhtkaasvp","resblock_name":"\u5b98\u5e84\u8c6a\u5ead","min_frame_area":"81","max_frame_area":"130","special_tags":[],"average_price":"5300","cover_pic":"http:\/\/image1.ljcdn.com\/xf-resblock\/1acbdad0-18a8-4f9c-9445-d214a3f0aaef.jpg.200x200.jpg","rooms":"3\u5c45\/2\u5c45","resblock_frame_area":"\u5efa\u9762 81~130m\u00b2","house_type":"\u666e\u901a\u4f4f\u5b85","url":"\/loupan\/p_gzhtkaasvp\/","price_show_config":"1","show_price":"5300","show_price_unit":"\u5143\/\u5e73","show_price_desc":"\u5747\u4ef7"}],"5212063303807224":[{"district_id":"23008857","longitude":"121.262511","latitude":"37.539189","resblock_id":"5212063303807224","project_name":"oshyaauyt","resblock_name":"\u6b27\u5c1a\u82b1\u56ed","min_frame_area":"53","max_frame_area":"110","special_tags":[],"average_price":"5300","cover_pic":"http:\/\/image1.ljcdn.com\/xf-resblock\/5bd19c98-8995-4569-a957-b61100a52001.jpg.200x200.jpg","rooms":"3\u5c45\/2\u5c45","resblock_frame_area":"\u5efa\u9762 53~110m\u00b2","house_type":"\u666e\u901a\u4f4f\u5b85","url":"\/loupan\/p_oshyaauyt\/","price_show_config":"1","show_price":"5300","show_price_unit":"\u5143\/\u5e73","show_price_desc":"\u5747\u4ef7"}],"5211062402627":[{"district_id":"23008857","longitude":"121.25315197681","latitude":"37.521088444182","resblock_id":"5211062402627","project_name":"unwlckaassq","resblock_name":"UN\u672a\u6765\u57ce","min_frame_area":"74","max_frame_area":"96","special_tags":[],"average_price":"5200","cover_pic":"http:\/\/image1.ljcdn.com\/xf-resblock\/a35953d4-877d-4230-a69e-a5d6d9ac2e6a.jpg.200x200.jpg","rooms":"3\u5c45\/2\u5c45","resblock_frame_area":"\u5efa\u9762 74~96m\u00b2","house_type":"\u666e\u901a\u4f4f\u5b85","url":"\/loupan\/p_unwlckaassq\/","price_show_config":"1","show_price":"5200","show_price_unit":"\u5143\/\u5e73","show_price_desc":"\u5747\u4ef7"}],"5212059997384815":[{"district_id":"23008858","longitude":"121.611266","latitude":"37.403176","resblock_id":"5212059997384815","project_name":"ddhfqjqaasto","resblock_name":"\u5927\u90fd\u6c47\u98ce\u60c5\u8857\u533a","min_frame_area":"87","max_frame_area":"119","special_tags":["\u7acb\u51cf1\u4e07"],"average_price":"5200","cover_pic":"http:\/\/image1.ljcdn.com\/xf-resblock\/d078a813-5068-4cc6-b797-749b5c5cd165.jpg.200x200.jpg","rooms":"3\u5c45\/2\u5c45","resblock_frame_area":"\u5efa\u9762 87~119m\u00b2","house_type":"\u666e\u901a\u4f4f\u5b85","url":"\/loupan\/p_ddhfqjqaasto\/","price_show_config":"1","show_price":"5200","show_price_unit":"\u5143\/\u5e73","show_price_desc":"\u5747\u4ef7"}],"5218060923907829":[{"district_id":"23008862","longitude":"119.971394","latitude":"37.204927","resblock_id":"5218060923907829","project_name":"hlkxcabahk","resblock_name":"\u6052\u9686\u51ef\u65cb\u57ce","min_frame_area":"78","max_frame_area":"82","special_tags":[],"average_price":"5200","cover_pic":"http:\/\/image1.ljcdn.com\/xf-resblock\/f17370c7-05f9-41a5-a189-552e11d74f79.jpg.200x200.jpg","rooms":"3\u5c45\/2\u5c45","resblock_frame_area":"\u5efa\u9762 78~82m\u00b2","house_type":"\u666e\u901a\u4f4f\u5b85","url":"\/loupan\/p_hlkxcabahk\/","price_show_config":"1","show_price":"5200","show_price_unit":"\u5143\/\u5e73","show_price_desc":"\u5747\u4ef7"}],"5211063135235":[{"district_id":"23008858","longitude":"121.59404809874","latitude":"37.405700912806","resblock_id":"5211063135235","project_name":"fyxckaasuy","resblock_name":"\u5bcc\u82d1\u65b0\u57ce","min_frame_area":"92","max_frame_area":"98","special_tags":["\u653f\u5e9c\u8865\u8d34"],"average_price":"5100","cover_pic":"http:\/\/image1.ljcdn.com\/xf-resblock\/73ac45e1-0403-471e-892b-19794aa4a990.jpg.200x200.jpg","rooms":"2\u5c45","resblock_frame_area":"\u5efa\u9762 92~98m\u00b2","house_type":"\u666e\u901a\u4f4f\u5b85","url":"\/loupan\/p_fyxckaasuy\/","price_show_config":"1","show_price":"5100","show_price_unit":"\u5143\/\u5e73","show_price_desc":"\u5747\u4ef7"}],"5217146792391264":[{"district_id":"23008857","longitude":"121.266275","latitude":"37.492741","resblock_id":"5217146792391264","project_name":"qlxzaayvi","resblock_name":"\u9752\u9f99\u5c0f\u9547","min_frame_area":"72","max_frame_area":"98","special_tags":[],"average_price":"5100","cover_pic":"http:\/\/image1.ljcdn.com\/xf-resblock\/756268f5-c6fa-4b6f-9eff-e4cee8918ca6.jpg.200x200.jpg","rooms":"3\u5c45\/2\u5c45","resblock_frame_area":"\u5efa\u9762 72~98m\u00b2","house_type":"\u666e\u901a\u4f4f\u5b85","url":"\/loupan\/p_qlxzaayvi\/","price_show_config":"1","show_price":"5100","show_price_unit":"\u5143\/\u5e73","show_price_desc":"\u5747\u4ef7"}],"5211062321614":[{"district_id":"23008857","longitude":"121.26763971339","latitude":"37.480039174974","resblock_id":"5211062321614","project_name":"jssyxaaspi","resblock_name":"\u541b\u5c71\u6c34","min_frame_area":"67","max_frame_area":"119","special_tags":[],"average_price":"5000","cover_pic":"http:\/\/image1.ljcdn.com\/xf-resblock\/ef8636f1-052d-4541-95ef-db0332efcbd6.jpg.200x200.jpg","rooms":"3\u5c45\/2\u5c45","resblock_frame_area":"\u5efa\u9762 67~119m\u00b2","house_type":"\u666e\u901a\u4f4f\u5b85","url":"\/loupan\/p_jssyxaaspi\/","price_show_config":"1","show_price":"5000","show_price_unit":"\u5143\/\u5e73","show_price_desc":"\u5747\u4ef7"}],"5211062326686":[{"district_id":"23008857","longitude":"121.266711","latitude":"37.479849","resblock_id":"5211062326686","project_name":"zwhykaaspr","resblock_name":"\u91d1\u8c61\u6cf0\u7d2b\u8587\u82b1\u56ed","min_frame_area":"72","max_frame_area":"126","special_tags":["\u5168\u6b3e9.2\u6298  \u8d37\u6b3e9.3\u6298"],"average_price":"5000","cover_pic":"http:\/\/image1.ljcdn.com\/xf-resblock\/799652b5-a3a8-4ec8-8ee5-199ea113de8d.jpg.200x200.jpg","rooms":"3\u5c45\/2\u5c45","resblock_frame_area":"\u5efa\u9762 72~126m\u00b2","house_type":"\u666e\u901a\u4f4f\u5b85","url":"\/loupan\/p_zwhykaaspr\/","price_show_config":"1","show_price":"5000","show_price_unit":"\u5143\/\u5e73","show_price_desc":"\u5747\u4ef7"}],"5212062179210094":[{"district_id":"23008857","longitude":"121.33671","latitude":"37.387699","resblock_id":"5212062179210094","project_name":"jhjyaaspu","resblock_name":"\u91d1\u534e\u5bb6\u56ed","min_frame_area":"75","max_frame_area":"90","special_tags":["\u83dc\u5730\u4f7f\u7528\u6743"],"average_price":"5000","cover_pic":"http:\/\/image1.ljcdn.com\/xf-resblock\/c6520d06-27f3-4de1-899f-03c64a1d39a3.jpg.200x200.jpg","rooms":"3\u5c45\/2\u5c45","resblock_frame_area":"\u5efa\u9762 75~90m\u00b2","house_type":"\u666e\u901a\u4f4f\u5b85","url":"\/loupan\/p_jhjyaaspu\/","price_show_config":"1","show_price":"5000","show_price_unit":"\u5143\/\u5e73","show_price_desc":"\u5747\u4ef7"}],"5212062179210023":[{"district_id":"23008857","longitude":"121.360858","latitude":"37.412163","resblock_id":"5212062179210023","project_name":"dmtxqaassr","resblock_name":"\u4e1c\u964c\u5802\u5982\u753b","min_frame_area":"56","max_frame_area":"91","special_tags":["\u4e07\u5143\u88c5\u4fee\u57fa\u91d1"],"average_price":"5000","cover_pic":"http:\/\/image1.ljcdn.com\/xf-resblock\/a3baab41-641f-4051-9238-97e33e089f60.jpg.200x200.jpg","rooms":"3\u5c45\/2\u5c45\/1\u5c45","resblock_frame_area":"\u5efa\u9762 56~91m\u00b2","house_type":"\u666e\u901a\u4f4f\u5b85","url":"\/loupan\/p_dmtxqaassr\/","price_show_config":"1","show_price":"5000","show_price_unit":"\u5143\/\u5e73","show_price_desc":"\u5747\u4ef7"}],"5212042968509816":[{"district_id":"23008858","longitude":"121.604765","latitude":"37.421678","resblock_id":"5212042968509816","project_name":"hygyaasxq","resblock_name":"\u6d77\u5c7f\u516c\u5143","min_frame_area":"81","max_frame_area":"122","special_tags":["\u5168\u6b3e9.5\u6298  \u8d37\u6b3e9.6\u6298"],"average_price":"5000","cover_pic":"http:\/\/image1.ljcdn.com\/xf-resblock\/85f4e529-455c-4058-8e38-e74059c8bd3b.jpg.200x200.jpg","rooms":"3\u5c45\/2\u5c45","resblock_frame_area":"\u5efa\u9762 81~122m\u00b2","house_type":"\u666e\u901a\u4f4f\u5b85","url":"\/loupan\/p_hygyaasxq\/","price_show_config":"1","show_price":"5000","show_price_unit":"\u5143\/\u5e73","show_price_desc":"\u5747\u4ef7"}],"5211063107448":[{"district_id":"23008858","longitude":"121.59752717589","latitude":"37.413625133773","resblock_id":"5211063107448","project_name":"tfxckaasxw","resblock_name":"\u5929\u798f\u65b0\u57ce","min_frame_area":"88","max_frame_area":"88","special_tags":["\u6bcf\u5e73\u7c73\u8865\u8d34"],"average_price":"5000","cover_pic":"http:\/\/image1.ljcdn.com\/xf-resblock\/4eac3a1b-2b80-49b5-92cc-353a24d10b15.jpg.200x200.jpg","rooms":"2\u5c45","resblock_frame_area":"\u5efa\u9762 88m\u00b2","house_type":"\u666e\u901a\u4f4f\u5b85","url":"\/loupan\/p_tfxckaasxw\/","price_show_config":"1","show_price":"5000","show_price_unit":"\u5143\/\u5e73","show_price_desc":"\u5747\u4ef7"}],"5212042352996515":[{"district_id":"23008858","longitude":"121.783994","latitude":"37.341546","resblock_id":"5212042352996515","project_name":"adlssmjaasyc","resblock_name":"\u5b89\u5fb7\u5229\u5c71\u6c34\u540d\u90e1","min_frame_area":"50","max_frame_area":"110","special_tags":["\u5168\u6b3e9.2\u6298  \u8d37\u6b3e9.5\u6298"],"average_price":"5000","cover_pic":"http:\/\/image1.ljcdn.com\/xf-resblock\/c81da85c-39dc-41e9-aacf-639169abad1a.jpg.200x200.jpg","rooms":"2\u5c45\/1\u5c45","resblock_frame_area":"\u5efa\u9762 50~110m\u00b2","house_type":"\u666e\u901a\u4f4f\u5b85","url":"\/loupan\/p_adlssmjaasyc\/","price_show_config":"1","show_price":"5000","show_price_unit":"\u5143\/\u5e73","show_price_desc":"\u5747\u4ef7"}],"5218062190348505":[{"district_id":"23008864","longitude":"120.421145","latitude":"37.381948","resblock_id":"5218062190348505","project_name":"lhgjcsxjqabahp","resblock_name":"\u4e3d\u6e56\u56fd\u9645\u57ce\u4e66\u9999\u5251\u6865","min_frame_area":"120","max_frame_area":"120","special_tags":[],"average_price":"5000","cover_pic":"http:\/\/image1.ljcdn.com\/xf-resblock\/ef0a8c0a-6607-4fff-b0ae-086683f8e362.jpg.200x200.jpg","rooms":"3\u5c45","resblock_frame_area":"\u5efa\u9762 120m\u00b2","house_type":"\u666e\u901a\u4f4f\u5b85","url":"\/loupan\/p_lhgjcsxjqabahp\/","price_show_config":"1","show_price":"5000","show_price_unit":"\u5143\/\u5e73","show_price_desc":"\u5747\u4ef7"}],"5218062228337559":[{"district_id":"23008864","longitude":"120.43082","latitude":"37.381992","resblock_id":"5218062228337559","project_name":"yjhcabahv","resblock_name":"\u5fa1\u666f\u534e\u57ce","min_frame_area":"93","max_frame_area":"93","special_tags":[],"average_price":"5000","cover_pic":"http:\/\/image1.ljcdn.com\/xf-resblock\/cbc388c6-206f-4e09-8106-4eabe960bdda.jpg.200x200.jpg","rooms":"2\u5c45","resblock_frame_area":"\u5efa\u9762 93m\u00b2","house_type":"\u666e\u901a\u4f4f\u5b85","url":"\/loupan\/p_yjhcabahv\/","price_show_config":"1","show_price":"5000","show_price_unit":"\u5143\/\u5e73","show_price_desc":"\u5747\u4ef7"}],"5212057791966381":[{"district_id":"23008858","longitude":"121.60279","latitude":"37.432468","resblock_id":"5212057791966381","project_name":"jyshlceqaasuq","resblock_name":"\u5efa\u6e90\u5c71\u6d77\u9f99\u57ce\u4e8c\u671f","min_frame_area":"83","max_frame_area":"133","special_tags":["\u5168\u6b3e9.8\u6298  \u8d37\u6b3e9.9\u6298"],"average_price":"4900","cover_pic":"http:\/\/image1.ljcdn.com\/xf-resblock\/dd7601fe-18ac-44b3-856a-c0a8490ac06b.jpg.200x200.jpg","rooms":"3\u5c45\/2\u5c45","resblock_frame_area":"\u5efa\u9762 83~133m\u00b2","house_type":"\u666e\u901a\u4f4f\u5b85","url":"\/loupan\/p_jyshlceqaasuq\/","price_show_config":"1","show_price":"4900","show_price_unit":"\u5143\/\u5e73","show_price_desc":"\u5747\u4ef7"}],"5212064089976029":[{"district_id":"23008858","longitude":"121.600899","latitude":"37.421496","resblock_id":"5212064089976029","project_name":"trjyaaswi","resblock_name":"\u5929\u6da6\u5bb6\u56ed","min_frame_area":"86","max_frame_area":"121","special_tags":["\u6bcf\u5e73\u4f18\u60e0"],"average_price":"4900","cover_pic":"http:\/\/image1.ljcdn.com\/xf-resblock\/f3a50255-6fcb-40ad-a132-6c267585ccbd.jpg.200x200.jpg","rooms":"4\u5c45\/3\u5c45","resblock_frame_area":"\u5efa\u9762 86~121m\u00b2","house_type":"\u666e\u901a\u4f4f\u5b85","url":"\/loupan\/p_trjyaaswi\/","price_show_config":"1","show_price":"4900","show_price_unit":"\u5143\/\u5e73","show_price_desc":"\u5747\u4ef7"}],"5212060222303247":[{"district_id":"23008858","longitude":"121.604783","latitude":"37.405971","resblock_id":"5212060222303247","project_name":"xykryaasmf","resblock_name":"\u96ea\u7389\u51ef\u745e\u82d1","min_frame_area":"82","max_frame_area":"121","special_tags":[],"average_price":"4800","cover_pic":"http:\/\/image1.ljcdn.com\/xf-resblock\/571d70b8-1911-4879-ab8a-6f33c5266ef8.jpg.200x200.jpg","rooms":"3\u5c45\/2\u5c45","resblock_frame_area":"\u5efa\u9762 82~121m\u00b2","house_type":"\u666e\u901a\u4f4f\u5b85","url":"\/loupan\/p_xykryaasmf\/","price_show_config":"1","show_price":"4800","show_price_unit":"\u5143\/\u5e73","show_price_desc":"\u5747\u4ef7"}],"5212047800873550":[{"district_id":"23008858","longitude":"121.614675","latitude":"37.424121","resblock_id":"5212047800873550","project_name":"xcsstaasut","resblock_name":"\u65b0\u6f6e\u5c1a\u4e66\u53f0","min_frame_area":"83","max_frame_area":"279","special_tags":["\u5168\u6b3e9.5\u6298  \u8d37\u6b3e9.6\u6298"],"average_price":"4800","cover_pic":"http:\/\/image1.ljcdn.com\/xf-resblock\/f6eaf9d8-2b10-4f1d-9e00-8f92e128c7f1.jpg.200x200.jpg","rooms":"5\u5c45\/4\u5c45\/3\u5c45\/2\u5c45","resblock_frame_area":"\u5efa\u9762 83~279m\u00b2","house_type":"\u666e\u901a\u4f4f\u5b85","url":"\/loupan\/p_xcsstaasut\/","price_show_config":"1","show_price":"4800","show_price_unit":"\u5143\/\u5e73","show_price_desc":"\u5747\u4ef7"}],"5212059838263140":[{"district_id":"23008857","longitude":"121.240844","latitude":"37.491766","resblock_id":"5212059838263140","project_name":"fllwhcaaspj","resblock_name":"\u798f\u5229\u83b1\u4e07\u548c\u57ce","min_frame_area":"41","max_frame_area":"140","special_tags":[],"average_price":"4750","cover_pic":"http:\/\/image1.ljcdn.com\/newhcms\/phpH3IcTt1470197977.png.200x200.jpg","rooms":"3\u5c45\/2\u5c45\/1\u5c45","resblock_frame_area":"\u5efa\u9762 41~140m\u00b2","house_type":"\u666e\u901a\u4f4f\u5b85","url":"\/loupan\/p_fllwhcaaspj\/","price_show_config":"1","show_price":"4750","show_price_unit":"\u5143\/\u5e73","show_price_desc":"\u5747\u4ef7"}],"5212042314198457":[{"district_id":"23008858","longitude":"121.589993","latitude":"37.416777","resblock_id":"5212042314198457","project_name":"jcsyhcaasxy","resblock_name":"\u5065\u6210\u6c34\u6f3e\u82b1\u57ce","min_frame_area":"76","max_frame_area":"113","special_tags":["\u6bcf\u5e73\u7c73\u4f18\u60e0"],"average_price":"4700","cover_pic":"http:\/\/image1.ljcdn.com\/xf-resblock\/9f82f054-2bbf-4289-8e3d-7d57e5ea5f89.jpg.200x200.jpg","rooms":"3\u5c45\/2\u5c45","resblock_frame_area":"\u5efa\u9762 76~113m\u00b2","house_type":"\u666e\u901a\u4f4f\u5b85","url":"\/loupan\/p_jcsyhcaasxy\/","price_show_config":"1","show_price":"4700","show_price_unit":"\u5143\/\u5e73","show_price_desc":"\u5747\u4ef7"}],"5211063135708":[{"district_id":"23008858","longitude":"121.59381183602","latitude":"37.421770823715","resblock_id":"5211063135708","project_name":"lhggkaawjp","resblock_name":"\u9886\u6d77\u516c\u9986","min_frame_area":"85","max_frame_area":"86","special_tags":["\u6bcf\u5e73\u7c73\u4f18\u60e0"],"average_price":"4700","cover_pic":"http:\/\/image1.ljcdn.com\/xf-resblock\/75573ecd-7c6d-4e1c-9257-5754263827bb.jpg.200x200.jpg","rooms":"2\u5c45","resblock_frame_area":"\u5efa\u9762 85~86m\u00b2","house_type":"\u666e\u901a\u4f4f\u5b85","url":"\/loupan\/p_lhggkaawjp\/","price_show_config":"1","show_price":"4700","show_price_unit":"\u5143\/\u5e73","show_price_desc":"\u5747\u4ef7"}],"5212063420460428":[{"district_id":"23008857","longitude":"121.211981","latitude":"37.475968","resblock_id":"5212063420460428","project_name":"yltaasqe","resblock_name":"\u60a6\u6f9c\u5ead","min_frame_area":"78","max_frame_area":"94","special_tags":["\u88c5\u4fee\u5bb6\u7535\u793c\u5305"],"average_price":"4600","cover_pic":"http:\/\/image1.ljcdn.com\/xf-resblock\/9118a035-c58f-458b-b270-277f42714a22.jpg.200x200.jpg","rooms":"3\u5c45\/2\u5c45","resblock_frame_area":"\u5efa\u9762 78~94m\u00b2","house_type":"\u666e\u901a\u4f4f\u5b85","url":"\/loupan\/p_yltaasqe\/","price_show_config":"1","show_price":"4600","show_price_unit":"\u5143\/\u5e73","show_price_desc":"\u5747\u4ef7"}],"5218059756603393":[{"district_id":"23008860","longitude":"120.514492","latitude":"37.660942","resblock_id":"5218059756603393","project_name":"sjygcabahx","resblock_name":"\u677e\u96bd\u9633\u5149\u57ce","min_frame_area":"80","max_frame_area":"80","special_tags":[],"average_price":"4600","cover_pic":"http:\/\/image1.ljcdn.com\/xf-resblock\/781fdbaf-d18a-42e1-8634-8df6dab49d87.jpg.200x200.jpg","rooms":"2\u5c45","resblock_frame_area":"\u5efa\u9762 80m\u00b2","house_type":"\u666e\u901a\u4f4f\u5b85","url":"\/loupan\/p_sjygcabahx\/","price_show_config":"1","show_price":"4600","show_price_unit":"\u5143\/\u5e73","show_price_desc":"\u5747\u4ef7"}],"5212057791966978":[{"district_id":"23008858","longitude":"121.600058","latitude":"37.381989","resblock_id":"5212057791966978","project_name":"fljyaasse","resblock_name":"\u798f\u4e34\u5bb6\u56ed","min_frame_area":"77","max_frame_area":"110","special_tags":[],"average_price":"4500","cover_pic":"http:\/\/image1.ljcdn.com\/xf-resblock\/8486343a-9fce-45ba-8f4f-ef7f45d0c522.jpg.200x200.jpg","rooms":"4\u5c45\/3\u5c45\/2\u5c45","resblock_frame_area":"\u5efa\u9762 77~110m\u00b2","house_type":"\u666e\u901a\u4f4f\u5b85","url":"\/loupan\/p_fljyaasse\/","price_show_config":"1","show_price":"4500","show_price_unit":"\u5143\/\u5e73","show_price_desc":"\u5747\u4ef7"}],"5211063121840":[{"district_id":"23008858","longitude":"121.568375","latitude":"37.409898","resblock_id":"5211063121840","project_name":"mcnhyxaasxt","resblock_name":"\u6162\u57ce\u5b81\u6d77","min_frame_area":"86","max_frame_area":"140","special_tags":["\u6bcf\u5e73\u7c73\u4f18\u60e0"],"average_price":"4500","cover_pic":"http:\/\/image1.ljcdn.com\/xf-resblock\/6152eb77-4050-4b06-9884-33d30010663e.jpg.200x200.jpg","rooms":"3\u5c45\/2\u5c45","resblock_frame_area":"\u5efa\u9762 86~140m\u00b2","house_type":"\u666e\u901a\u4f4f\u5b85","url":"\/loupan\/p_mcnhyxaasxt\/","price_show_config":"1","show_price":"4500","show_price_unit":"\u5143\/\u5e73","show_price_desc":"\u5747\u4ef7"}],"5212041874321203":[{"district_id":"23009088","longitude":"121.557914","latitude":"37.404919","resblock_id":"5212041874321203","project_name":"xrhchysjaasyl","resblock_name":"\u65ed\u745e\u548c\u660c\u6d77\u9038\u4e16\u5bb6","min_frame_area":"80","max_frame_area":"99","special_tags":[],"average_price":"4500","cover_pic":"http:\/\/image1.ljcdn.com\/xf-resblock\/dd81f957-75fd-4052-b46a-a344949f40ed.jpg.200x200.jpg","rooms":"3\u5c45\/2\u5c45","resblock_frame_area":"\u5efa\u9762 80~99m\u00b2","house_type":"\u666e\u901a\u4f4f\u5b85","url":"\/loupan\/p_xrhchysjaasyl\/","price_show_config":"1","show_price":"4500","show_price_unit":"\u5143\/\u5e73","show_price_desc":"\u5747\u4ef7"}],"5212047205281607":[{"district_id":"23008857","longitude":"121.258846","latitude":"37.476756","resblock_id":"5212047205281607","project_name":"tyycshaasor","resblock_name":"\u901a\u7528\u4e00\u57ce\u5c71\u6cb3","min_frame_area":"77","max_frame_area":"95","special_tags":[],"average_price":"4400","cover_pic":"http:\/\/image1.ljcdn.com\/xf-resblock\/e07074c1-c11d-4526-ba27-3922031100f3.jpg.200x200.jpg","rooms":"2\u5c45","resblock_frame_area":"\u5efa\u9762 77~95m\u00b2","house_type":"\u666e\u901a\u4f4f\u5b85","url":"\/loupan\/p_tyycshaasor\/","price_show_config":"1","show_price":"4400","show_price_unit":"\u5143\/\u5e73","show_price_desc":"\u5747\u4ef7"}],"5212195991924837":[{"district_id":"23008858","longitude":"121.58862","latitude":"37.382388","resblock_id":"5212195991924837","project_name":"mcctaasuc","resblock_name":"\u725f\u57ce\u6625\u5929","min_frame_area":"83","max_frame_area":"130","special_tags":["\u6bcf\u5e73\u7c73\u4f18\u60e0"],"average_price":"4400","cover_pic":"http:\/\/image1.ljcdn.com\/xf-resblock\/687cb1ca-0bb2-409d-8c9a-18368db2da65.jpg.200x200.jpg","rooms":"3\u5c45\/2\u5c45","resblock_frame_area":"\u5efa\u9762 83~130m\u00b2","house_type":"\u666e\u901a\u4f4f\u5b85","url":"\/loupan\/p_mcctaasuc\/","price_show_config":"1","show_price":"4400","show_price_unit":"\u5143\/\u5e73","show_price_desc":"\u5747\u4ef7"}],"5211063057792":[{"district_id":"23008858","longitude":"121.60511008557","latitude":"37.396138727462","resblock_id":"5211063057792","project_name":"ltcsgckaasve","resblock_name":"\u84dd\u5929\u57ce\u5e02\u5e7f\u573a","min_frame_area":"99","max_frame_area":"107","special_tags":["\u6bcf\u5e73\u4f18\u60e0"],"average_price":"4400","cover_pic":"http:\/\/image1.ljcdn.com\/xf-resblock\/e9d421b9-8bd4-4b68-96a1-5110f3e7f319.jpg.200x200.jpg","rooms":"3\u5c45","resblock_frame_area":"\u5efa\u9762 99~107m\u00b2","house_type":"\u666e\u901a\u4f4f\u5b85","url":"\/loupan\/p_ltcsgckaasve\/","price_show_config":"1","show_price":"4400","show_price_unit":"\u5143\/\u5e73","show_price_desc":"\u5747\u4ef7"}],"5211062488591":[{"district_id":"23009087","longitude":"121.12804465638","latitude":"37.588594600508","resblock_id":"5211062488591","project_name":"aasre","resblock_name":"\u901a\u7528\u5bcc\u99a8\u4f73\u82d1","min_frame_area":"87","max_frame_area":"93","special_tags":[],"average_price":"4300","cover_pic":"http:\/\/image1.ljcdn.com\/xf-resblock\/91d1cb7a-d386-4eff-8aff-b3b615415368.jpg.200x200.jpg","rooms":"2\u5c45","resblock_frame_area":"\u5efa\u9762 87~93m\u00b2","house_type":"\u666e\u901a\u4f4f\u5b85","url":"\/loupan\/p_aasre\/","price_show_config":"1","show_price":"4300","show_price_unit":"\u5143\/\u5e73","show_price_desc":"\u5747\u4ef7"}],"5217817185847813":[{"district_id":"23008858","longitude":"121.595136","latitude":"37.384369","resblock_id":"5217817185847813","project_name":"hlgjaazrx","resblock_name":"\u6d77\u4f26\u56fd\u9645","min_frame_area":"111","max_frame_area":"137","special_tags":[],"average_price":"4300","cover_pic":"http:\/\/image1.ljcdn.com\/xf-resblock\/01ec98c6-c7e4-4279-9c73-1735e6586881.jpg.200x200.jpg","rooms":"3\u5c45","resblock_frame_area":"\u5efa\u9762 111~137m\u00b2","house_type":"\u666e\u901a\u4f4f\u5b85","url":"\/loupan\/p_hlgjaazrx\/","price_show_config":"1","show_price":"4300","show_price_unit":"\u5143\/\u5e73","show_price_desc":"\u5747\u4ef7"}],"5218061934758204":[{"district_id":"23008864","longitude":"120.409091","latitude":"37.379985","resblock_id":"5218061934758204","project_name":"xysjabaha","resblock_name":"\u5174\u60a6\u4e16\u5609","min_frame_area":"80","max_frame_area":"80","special_tags":[],"average_price":"4300","cover_pic":"http:\/\/image1.ljcdn.com\/xf-resblock\/f873062d-644a-4b46-893d-d850b74b7cba.jpg.200x200.jpg","rooms":"2\u5c45","resblock_frame_area":"\u5efa\u9762 80m\u00b2","house_type":"\u666e\u901a\u4f4f\u5b85","url":"\/loupan\/p_xysjabaha\/","price_show_config":"1","show_price":"4300","show_price_unit":"\u5143\/\u5e73","show_price_desc":"\u5747\u4ef7"}],"5212060168302839":[{"district_id":"23008857","longitude":"121.215763","latitude":"37.478795","resblock_id":"5212060168302839","project_name":"xcjysyaaspn","resblock_name":"\u4e61\u6751\u8bb0\u5fc6\u00b7\u5c71\u6c34\u56ed","min_frame_area":"87","max_frame_area":"90","special_tags":[],"average_price":"4200","cover_pic":"http:\/\/image1.ljcdn.com\/xf-resblock\/d21d8049-7cd1-42b6-8eb7-c6d7cb4998fc.jpg.200x200.jpg","rooms":"2\u5c45","resblock_frame_area":"\u5efa\u9762 87~90m\u00b2","house_type":"\u666e\u901a\u4f4f\u5b85","url":"\/loupan\/p_xcjysyaaspn\/","price_show_config":"1","show_price":"4200","show_price_unit":"\u5143\/\u5e73","show_price_desc":"\u5747\u4ef7"}],"5212063118995967":[{"district_id":"23008857","longitude":"121.30315","latitude":"37.464598","resblock_id":"5212063118995967","project_name":"yfflxcaaspw","resblock_name":"\u4e49\u4e30\u5bcc\u4e3d\u65b0\u57ce","min_frame_area":"55","max_frame_area":"102","special_tags":["\u88c5\u4fee\u5bb6\u7535\u8865\u8d34"],"average_price":"4200","cover_pic":"http:\/\/image1.ljcdn.com\/xf-resblock\/bc20ba8d-000b-4e6b-ae3f-4c33b9640a94.jpg.200x200.jpg","rooms":"3\u5c45\/2\u5c45\/1\u5c45","resblock_frame_area":"\u5efa\u9762 55~102m\u00b2","house_type":"\u666e\u901a\u4f4f\u5b85","url":"\/loupan\/p_yfflxcaaspw\/","price_show_config":"1","show_price":"4200","show_price_unit":"\u5143\/\u5e73","show_price_desc":"\u5747\u4ef7"}],"5212063778287789":[{"district_id":"23008857","longitude":"121.245767","latitude":"37.41844","resblock_id":"5212063778287789","project_name":"xyhpaasqj","resblock_name":"\u9999\u9038\u6e56\u7554","min_frame_area":"83","max_frame_area":"94","special_tags":[],"average_price":"4100","cover_pic":"http:\/\/image1.ljcdn.com\/xf-resblock\/22196f69-fab5-49ea-baaf-82997c1a327e.jpg.200x200.jpg","rooms":"3\u5c45\/2\u5c45","resblock_frame_area":"\u5efa\u9762 83~94m\u00b2","house_type":"\u666e\u901a\u4f4f\u5b85","url":"\/loupan\/p_xyhpaasqj\/","price_show_config":"1","show_price":"4100","show_price_unit":"\u5143\/\u5e73","show_price_desc":"\u5747\u4ef7"}],"5212063368294221":[{"district_id":"23008857","longitude":"121.216518","latitude":"37.478173","resblock_id":"5212063368294221","project_name":"fyyjaasqc","resblock_name":"\u798f\u7f18\u96c5\u5c45","min_frame_area":"76","max_frame_area":"94","special_tags":[],"average_price":"4000","cover_pic":"http:\/\/image1.ljcdn.com\/xf-resblock\/b029a09c-f900-4d88-8596-b282c892af25.jpg.200x200.jpg","rooms":"3\u5c45\/2\u5c45","resblock_frame_area":"\u5efa\u9762 76~94m\u00b2","house_type":"\u666e\u901a\u4f4f\u5b85","url":"\/loupan\/p_fyyjaasqc\/","price_show_config":"1","show_price":"4000","show_price_unit":"\u5143\/\u5e73","show_price_desc":"\u5747\u4ef7"}],"5212047205281609":[{"district_id":"23008858","longitude":"121.593285","latitude":"37.389071","resblock_id":"5212047205281609","project_name":"dtbhyaasvl","resblock_name":"\u4e1c\u6cf0\u767e\u5408\u82d1","min_frame_area":"67","max_frame_area":"96","special_tags":["\u5168\u6b3e9.6\u6298  \u8d37\u6b3e9.8\u6298"],"average_price":"3850","cover_pic":"http:\/\/image1.ljcdn.com\/xf-resblock\/b245cd68-aa8b-4d09-8abb-b58de52ded43.jpg.200x200.jpg","rooms":"3\u5c45\/2\u5c45","resblock_frame_area":"\u5efa\u9762 67~96m\u00b2","house_type":"\u666e\u901a\u4f4f\u5b85","url":"\/loupan\/p_dtbhyaasvl\/","price_show_config":"1","show_price":"3850","show_price_unit":"\u5143\/\u5e73","show_price_desc":"\u5747\u4ef7"}],"5218061728428248":[{"district_id":"23008860","longitude":"120.425333","latitude":"37.716963","resblock_id":"5218061728428248","project_name":"hlfabahq","resblock_name":"\u6d77\u7acb\u65b9","min_frame_area":"76","max_frame_area":"76","special_tags":["\u6bcf\u5e73\u4f18\u60e0"],"average_price":"3780","cover_pic":"http:\/\/image1.ljcdn.com\/xf-resblock\/f19e91cd-8299-4163-bad8-9b5b9cd31c64.jpg.200x200.jpg","rooms":"2\u5c45","resblock_frame_area":"\u5efa\u9762 76m\u00b2","house_type":"\u666e\u901a\u4f4f\u5b85","url":"\/loupan\/p_hlfabahq\/","price_show_config":"1","show_price":"3780","show_price_unit":"\u5143\/\u5e73","show_price_desc":"\u5747\u4ef7"}],"5218061520022602":[{"district_id":"23008860","longitude":"120.476098","latitude":"37.736919","resblock_id":"5218061520022602","project_name":"htjabahl","resblock_name":"\u6d77\u6cf0\u5c45","min_frame_area":"59","max_frame_area":"59","special_tags":["\u6bcf\u5e73\u4f18\u60e0"],"average_price":"3700","cover_pic":"http:\/\/image1.ljcdn.com\/xf-resblock\/d2dcc15f-37a8-4b7c-b6d3-704452ef9187.jpg.200x200.jpg","rooms":"2\u5c45","resblock_frame_area":"\u5efa\u9762 59m\u00b2","house_type":"\u666e\u901a\u4f4f\u5b85","url":"\/loupan\/p_htjabahl\/","price_show_config":"1","show_price":"3700","show_price_unit":"\u5143\/\u5e73","show_price_desc":"\u5747\u4ef7"}],"5214171959757791":[{"district_id":"23008858","longitude":"121.638393","latitude":"37.397382","resblock_id":"5214171959757791","project_name":"lyygcaawdk","resblock_name":"\u9f99\u71d5\u9633\u5149\u57ce","min_frame_area":"90","max_frame_area":"110","special_tags":["9.8\u6298"],"average_price":"3600","cover_pic":"http:\/\/image1.ljcdn.com\/xf-resblock\/e98afc3f-213c-4c7f-80a3-933b91605f99.jpg.200x200.jpg","rooms":"3\u5c45\/2\u5c45","resblock_frame_area":"\u5efa\u9762 90~110m\u00b2","house_type":"\u666e\u901a\u4f4f\u5b85","url":"\/loupan\/p_lyygcaawdk\/","price_show_config":"1","show_price":"3600","show_price_unit":"\u5143\/\u5e73","show_price_desc":"\u5747\u4ef7"}],"5218060923907574":[{"district_id":"23008860","longitude":"120.438334","latitude":"37.710689","resblock_id":"5218060923907574","project_name":"hghjbqabahy","resblock_name":"\u6e56\u5149\u6d77\u666fB\u533a","min_frame_area":"51","max_frame_area":"51","special_tags":[],"average_price":"3400","cover_pic":"http:\/\/image1.ljcdn.com\/xf-resblock\/8285656d-c27b-4f75-8897-fd08c8ab124f.jpg.200x200.jpg","rooms":"1\u5c45","resblock_frame_area":"\u5efa\u9762 51m\u00b2","house_type":"\u666e\u901a\u4f4f\u5b85","url":"\/loupan\/p_hghjbqabahy\/","price_show_config":"1","show_price":"3400","show_price_unit":"\u5143\/\u5e73","show_price_desc":"\u5747\u4ef7"}],"5218061213839620":[{"district_id":"23008860","longitude":"120.389488","latitude":"37.700073","resblock_id":"5218061213839620","project_name":"bhscabahh","resblock_name":"\u78a7\u6d77\u5c1a\u57ce","min_frame_area":"65","max_frame_area":"65","special_tags":[],"average_price":"3300","cover_pic":"http:\/\/image1.ljcdn.com\/xf-resblock\/2e23e964-42c1-492e-9622-83ea6ed432bd.jpg.200x200.jpg","rooms":"2\u5c45","resblock_frame_area":"\u5efa\u9762 65m\u00b2","house_type":"\u666e\u901a\u4f4f\u5b85","url":"\/loupan\/p_bhscabahh\/","price_show_config":"1","show_price":"3300","show_price_unit":"\u5143\/\u5e73","show_price_desc":"\u5747\u4ef7"}],"5218060660715031":[{"district_id":"23008860","longitude":"120.446902","latitude":"37.722087","resblock_id":"5218060660715031","project_name":"hghjabahw","resblock_name":"\u6e56\u5149\u8c6a\u666f","min_frame_area":"62","max_frame_area":"62","special_tags":[],"average_price":"3300","cover_pic":"http:\/\/image1.ljcdn.com\/xf-resblock\/f1dd0de0-1171-43a4-8318-77f14106ec80.jpg.200x200.jpg","rooms":"1\u5c45","resblock_frame_area":"\u5efa\u9762 62m\u00b2","house_type":"\u666e\u901a\u4f4f\u5b85","url":"\/loupan\/p_hghjabahw\/","price_show_config":"1","show_price":"3300","show_price_unit":"\u5143\/\u5e73","show_price_desc":"\u5747\u4ef7"}],"5212042314198629":[{"district_id":"23008858","longitude":"121.747757","latitude":"37.286154","resblock_id":"5212042314198629","project_name":"tjkyzgyzaasxx","resblock_name":"\u5929\u5883\u6606\u5d5b\u4e2d\u56fd\u9662\u5b50","min_frame_area":"52","max_frame_area":"89","special_tags":[],"average_price":0,"cover_pic":"http:\/\/image1.ljcdn.com\/xf-resblock\/981e761f-11ce-4e21-a091-41ef3d26cd9c.jpg.200x200.jpg","rooms":"2\u5c45\/1\u5c45","resblock_frame_area":"\u5efa\u9762 52~89m\u00b2","house_type":"\u666e\u901a\u4f4f\u5b85","url":"\/loupan\/p_tjkyzgyzaasxx\/","price_show_config":"3","show_price":"60","show_price_unit":"\u4e07\/\u5957","show_price_desc":"\u5747\u4ef7"}]}}